[
  {
    "id": 1,
    "omikujiGroupId": 1,
    "unit": "piapro",
    "fortuneType": "grate_fortune",
    "summary": "若能关怀他人，\n就将收获许多邂逅，\n这一年注定会美好。",
    "title1": "愿望",
    "description1": "愿望定将实现。",
    "title2": "健康",
    "description2": "情况非常好。\n进行运动会更好。",
    "title3": "等候之人",
    "description3": "一定会到来。",
    "unitAssetbundleName": "lottery_game\/new_year_2022_material",
    "fortuneAssetbundleName": "lottery_game\/new_year_2022_material",
    "omikujiCoverAssetbundleName": "lottery_game\/new_year_2022_material",
    "unitFilePath": "bird_VIRTUAL SINGER",
    "fortuneFilePath": "unsei_daikichi",
    "omikujiCoverFilePath": "omikuji_VIRTUAL SINGER"
  },
  {
    "id": 2,
    "omikujiGroupId": 1,
    "unit": "piapro",
    "fortuneType": "fortune",
    "summary": "今年会是丰收之年，\n你会为许多人加油打气，\n并得到许多人的支持。",
    "title1": "愿望",
    "description1": "愿望应该会顺利实现。",
    "title2": "健康",
    "description2": "情况良好。",
    "title3": "等候之人",
    "description3": "只要怀抱信念就会到来。",
    "unitAssetbundleName": "lottery_game\/new_year_2022_material",
    "fortuneAssetbundleName": "lottery_game\/new_year_2022_material",
    "omikujiCoverAssetbundleName": "lottery_game\/new_year_2022_material",
    "unitFilePath": "bird_VIRTUAL SINGER",
    "fortuneFilePath": "unsei_kichi",
    "omikujiCoverFilePath": "omikuji_VIRTUAL SINGER"
  },
  {
    "id": 3,
    "omikujiGroupId": 1,
    "unit": "piapro",
    "fortuneType": "middle_fortune",
    "summary": "这会是充满机遇的一年。\n你将因为不同的邂逅和体验，\n获得成长的机会。",
    "title1": "愿望",
    "description1": "团队合作是成功的关键，\n团结一致愿望就能实现。",
    "title2": "健康",
    "description2": "情况良好。",
    "title3": "等候之人",
    "description3": "虽会迟到，\n 但一定会到来。",
    "unitAssetbundleName": "lottery_game\/new_year_2022_material",
    "fortuneAssetbundleName": "lottery_game\/new_year_2022_material",
    "omikujiCoverAssetbundleName": "lottery_game\/new_year_2022_material",
    "unitFilePath": "bird_VIRTUAL SINGER",
    "fortuneFilePath": "unsei_cyukichi",
    "omikujiCoverFilePath": "omikuji_VIRTUAL SINGER"
  },
  {
    "id": 4,
    "omikujiGroupId": 1,
    "unit": "piapro",
    "fortuneType": "small_fortune",
    "summary": "因为你的善解人意和助人为乐，\n围绕在你身边的问题\n将迎刃而解。",
    "title1": "愿望",
    "description1": "采取行动，\n愿望就能实现。",
    "title2": "健康",
    "description2": "没有问题。",
    "title3": "等候之人",
    "description3": "不久后便会到来。",
    "unitAssetbundleName": "lottery_game\/new_year_2022_material",
    "fortuneAssetbundleName": "lottery_game\/new_year_2022_material",
    "omikujiCoverAssetbundleName": "lottery_game\/new_year_2022_material",
    "unitFilePath": "bird_VIRTUAL SINGER",
    "fortuneFilePath": "unsei_syoukichi",
    "omikujiCoverFilePath": "omikuji_VIRTUAL SINGER"
  },
  {
    "id": 5,
    "omikujiGroupId": 1,
    "unit": "piapro",
    "fortuneType": "uncertain_luck",
    "summary": "这会是风平浪静的一年。\n助人为乐是获得\n好运的关键。",
    "title1": "愿望",
    "description1": "尽管会耗费时间，\n但愿望应该能实现。",
    "title2": "健康",
    "description2": "虽然没有问题，\n但切忌暴饮暴食。",
    "title3": "等候之人",
    "description3": "亲自前往寻找\n 为明智之举。",
    "unitAssetbundleName": "lottery_game\/new_year_2022_material",
    "fortuneAssetbundleName": "lottery_game\/new_year_2022_material",
    "omikujiCoverAssetbundleName": "lottery_game\/new_year_2022_material",
    "unitFilePath": "bird_VIRTUAL SINGER",
    "fortuneFilePath": "unsei_suekichi",
    "omikujiCoverFilePath": "omikuji_VIRTUAL SINGER"
  },
  {
    "id": 6,
    "omikujiGroupId": 1,
    "unit": "piapro",
    "fortuneType": "misfortune",
    "summary": "你可能会受到\n周围情况的影响，\n许多事无法按计划进行。",
    "title1": "愿望",
    "description1": "愿望能够实现，\n但会遇到诸多困难。",
    "title2": "健康",
    "description2": "要注意身体的保暖。",
    "title3": "等候之人",
    "description3": "会晚来。",
    "unitAssetbundleName": "lottery_game\/new_year_2022_material",
    "fortuneAssetbundleName": "lottery_game\/new_year_2022_material",
    "omikujiCoverAssetbundleName": "lottery_game\/new_year_2022_material",
    "unitFilePath": "bird_VIRTUAL SINGER",
    "fortuneFilePath": "unsei_kyou",
    "omikujiCoverFilePath": "omikuji_VIRTUAL SINGER"
  },
  {
    "id": 7,
    "omikujiGroupId": 1,
    "unit": "piapro",
    "fortuneType": "grate_misfortune",
    "summary": "人的想法\n难以轻易改变，\n静待转机方为明智之举。",
    "title1": "愿望",
    "description1": "愿望应该很难实现。",
    "title2": "健康",
    "description2": "面对持续的烦恼，\n有时需要让身心得到休息。",
    "title3": "等候之人",
    "description3": "暂时不会到来。",
    "unitAssetbundleName": "lottery_game\/new_year_2022_material",
    "fortuneAssetbundleName": "lottery_game\/new_year_2022_material",
    "omikujiCoverAssetbundleName": "lottery_game\/new_year_2022_material",
    "unitFilePath": "bird_VIRTUAL SINGER",
    "fortuneFilePath": "unsei_daikyou",
    "omikujiCoverFilePath": "omikuji_VIRTUAL SINGER"
  },
  {
    "id": 8,
    "omikujiGroupId": 1,
    "unit": "light_sound",
    "fortuneType": "grate_fortune",
    "summary": "你将与疏远之友\n重拾联络。",
    "title1": "愿望",
    "description1": "尽管会遇到诸多困难，\n但愿望一定会实现。",
    "title2": "健康",
    "description2": "情况非常好。",
    "title3": "等候之人",
    "description3": "一定会到来。",
    "unitAssetbundleName": "lottery_game\/new_year_2022_material",
    "fortuneAssetbundleName": "lottery_game\/new_year_2022_material",
    "omikujiCoverAssetbundleName": "lottery_game\/new_year_2022_material",
    "unitFilePath": "bird_Leoneed",
    "fortuneFilePath": "unsei_daikichi",
    "omikujiCoverFilePath": "omikuji_Leoneed"
  },
  {
    "id": 9,
    "omikujiGroupId": 1,
    "unit": "light_sound",
    "fortuneType": "fortune",
    "summary": "今年是离实现梦想\n最近的一年，\n好好珍惜过往的缘分吧。",
    "title1": "愿望",
    "description1": "能得到他人帮助，\n离实现愿望更近一步。",
    "title2": "健康",
    "description2": "情况良好。",
    "title3": "等候之人",
    "description3": "不久后便会到来。",
    "unitAssetbundleName": "lottery_game\/new_year_2022_material",
    "fortuneAssetbundleName": "lottery_game\/new_year_2022_material",
    "omikujiCoverAssetbundleName": "lottery_game\/new_year_2022_material",
    "unitFilePath": "bird_Leoneed",
    "fortuneFilePath": "unsei_kichi",
    "omikujiCoverFilePath": "omikuji_Leoneed"
  },
  {
    "id": 10,
    "omikujiGroupId": 1,
    "unit": "light_sound",
    "fortuneType": "middle_fortune",
    "summary": "今年周围环境\n会发生剧变，\n你的行动可能是转机的关键。",
    "title1": "愿望",
    "description1": "尽管会面临诸多阻碍，\n但愿望会实现。",
    "title2": "健康",
    "description2": "虽然基本上没有问题，\n但不能勉强自己。",
    "title3": "等候之人",
    "description3": "一定会到来。",
    "unitAssetbundleName": "lottery_game\/new_year_2022_material",
    "fortuneAssetbundleName": "lottery_game\/new_year_2022_material",
    "omikujiCoverAssetbundleName": "lottery_game\/new_year_2022_material",
    "unitFilePath": "bird_Leoneed",
    "fortuneFilePath": "unsei_cyukichi",
    "omikujiCoverFilePath": "omikuji_Leoneed"
  },
  {
    "id": 11,
    "omikujiGroupId": 1,
    "unit": "light_sound",
    "fortuneType": "small_fortune",
    "summary": "虽然不是所有事情\n都会一帆风顺，\n但这一年你将坚实地向前迈进。",
    "title1": "愿望",
    "description1": "愿望基本会实现。",
    "title2": "健康",
    "description2": "要注意饮食均衡。",
    "title3": "等候之人",
    "description3": "会晚一些到来。",
    "unitAssetbundleName": "lottery_game\/new_year_2022_material",
    "fortuneAssetbundleName": "lottery_game\/new_year_2022_material",
    "omikujiCoverAssetbundleName": "lottery_game\/new_year_2022_material",
    "unitFilePath": "bird_Leoneed",
    "fortuneFilePath": "unsei_syoukichi",
    "omikujiCoverFilePath": "omikuji_Leoneed"
  },
  {
    "id": 12,
    "omikujiGroupId": 1,
    "unit": "light_sound",
    "fortuneType": "uncertain_luck",
    "summary": "与伙伴一同\n从零开始挑战，\n便能开启一条崭新的道路。",
    "title1": "愿望",
    "description1": "尽管会耗费时间，\n但愿望应该能实现。",
    "title2": "健康",
    "description2": "没有问题。",
    "title3": "等候之人",
    "description3": "会到来。",
    "unitAssetbundleName": "lottery_game\/new_year_2022_material",
    "fortuneAssetbundleName": "lottery_game\/new_year_2022_material",
    "omikujiCoverAssetbundleName": "lottery_game\/new_year_2022_material",
    "unitFilePath": "bird_Leoneed",
    "fortuneFilePath": "unsei_suekichi",
    "omikujiCoverFilePath": "omikuji_Leoneed"
  },
  {
    "id": 13,
    "omikujiGroupId": 1,
    "unit": "light_sound",
    "fortuneType": "misfortune",
    "summary": "这一年中想法越多\n便越容易错过良机，\n如果你敢于面对便会迎来转机。",
    "title1": "愿望",
    "description1": "不付出行动愿望就不会实现。",
    "title2": "健康",
    "description2": "有迹象表明\n你会因烦恼而感到疲惫。",
    "title3": "等候之人",
    "description3": "会晚来。",
    "unitAssetbundleName": "lottery_game\/new_year_2022_material",
    "fortuneAssetbundleName": "lottery_game\/new_year_2022_material",
    "omikujiCoverAssetbundleName": "lottery_game\/new_year_2022_material",
    "unitFilePath": "bird_Leoneed",
    "fortuneFilePath": "unsei_kyou",
    "omikujiCoverFilePath": "omikuji_Leoneed"
  },
  {
    "id": 14,
    "omikujiGroupId": 1,
    "unit": "light_sound",
    "fortuneType": "grate_misfortune",
    "summary": "在人际交往方面你会遇到困难，\n选择那些真正值得珍惜的人交往\n方为明智之举。",
    "title1": "愿望",
    "description1": "不公开愿望就不会实现。",
    "title2": "健康",
    "description2": "会有饮食方面的问题。\n需避免暴饮暴食。",
    "title3": "等候之人",
    "description3": "不会到来，\n 亲自前往寻找会更快。",
    "unitAssetbundleName": "lottery_game\/new_year_2022_material",
    "fortuneAssetbundleName": "lottery_game\/new_year_2022_material",
    "omikujiCoverAssetbundleName": "lottery_game\/new_year_2022_material",
    "unitFilePath": "bird_Leoneed",
    "fortuneFilePath": "unsei_daikyou",
    "omikujiCoverFilePath": "omikuji_Leoneed"
  },
  {
    "id": 15,
    "omikujiGroupId": 1,
    "unit": "idol",
    "fortuneType": "grate_fortune",
    "summary": "至今为止的努力与心愿\n将会开花结果，\n这一年你将离憧憬的梦想更近一步。",
    "title1": "愿望",
    "description1": "即使遇到困难，\n愿望也应该能实现。",
    "title2": "健康",
    "description2": "多运动，\n体力应该就会变好。",
    "title3": "等候之人",
    "description3": "应该会到来。",
    "unitAssetbundleName": "lottery_game\/new_year_2022_material",
    "fortuneAssetbundleName": "lottery_game\/new_year_2022_material",
    "omikujiCoverAssetbundleName": "lottery_game\/new_year_2022_material",
    "unitFilePath": "bird_MORE MORE JUMP",
    "fortuneFilePath": "unsei_daikichi",
    "omikujiCoverFilePath": "omikuji_MORE MORE JUMP"
  },
  {
    "id": 16,
    "omikujiGroupId": 1,
    "unit": "idol",
    "fortuneType": "fortune",
    "summary": "这一年中\n你的忧郁会一扫而空，\n能以最真实的面貌度过。",
    "title1": "愿望",
    "description1": "愿望能够实现。",
    "title2": "健康",
    "description2": "应该能健康度过。",
    "title3": "等候之人",
    "description3": "会到来。",
    "unitAssetbundleName": "lottery_game\/new_year_2022_material",
    "fortuneAssetbundleName": "lottery_game\/new_year_2022_material",
    "omikujiCoverAssetbundleName": "lottery_game\/new_year_2022_material",
    "unitFilePath": "bird_MORE MORE JUMP",
    "fortuneFilePath": "unsei_kichi",
    "omikujiCoverFilePath": "omikuji_MORE MORE JUMP"
  },
  {
    "id": 17,
    "omikujiGroupId": 1,
    "unit": "idol",
    "fortuneType": "middle_fortune",
    "summary": "这一年中\n你日积月累的成果，\n会逐渐展现出来。",
    "title1": "愿望",
    "description1": "会出现支持你的人，\n愿望应该能够实现。",
    "title2": "健康",
    "description2": "情况良好。",
    "title3": "等候之人",
    "description3": "会在身边人的帮助下遇见。",
    "unitAssetbundleName": "lottery_game\/new_year_2022_material",
    "fortuneAssetbundleName": "lottery_game\/new_year_2022_material",
    "omikujiCoverAssetbundleName": "lottery_game\/new_year_2022_material",
    "unitFilePath": "bird_MORE MORE JUMP",
    "fortuneFilePath": "unsei_cyukichi",
    "omikujiCoverFilePath": "omikuji_MORE MORE JUMP"
  },
  {
    "id": 18,
    "omikujiGroupId": 1,
    "unit": "idol",
    "fortuneType": "small_fortune",
    "summary": "你将获得契机，\n重拾一度放弃的目标。",
    "title1": "愿望",
    "description1": "会出现支持你的朋友，\n愿望应该能实现。",
    "title2": "健康",
    "description2": "没有问题。",
    "title3": "等候之人",
    "description3": "也许会在不经意间到来。",
    "unitAssetbundleName": "lottery_game\/new_year_2022_material",
    "fortuneAssetbundleName": "lottery_game\/new_year_2022_material",
    "omikujiCoverAssetbundleName": "lottery_game\/new_year_2022_material",
    "unitFilePath": "bird_MORE MORE JUMP",
    "fortuneFilePath": "unsei_syoukichi",
    "omikujiCoverFilePath": "omikuji_MORE MORE JUMP"
  },
  {
    "id": 19,
    "omikujiGroupId": 1,
    "unit": "idol",
    "fortuneType": "uncertain_luck",
    "summary": "现在正是忍耐之时，\n应为实现梦想打好基础。",
    "title1": "愿望",
    "description1": "会出现带给你希望的人，\n愿望应该能够实现。",
    "title2": "健康",
    "description2": "没有问题。",
    "title3": "等候之人",
    "description3": "应该会到来。",
    "unitAssetbundleName": "lottery_game\/new_year_2022_material",
    "fortuneAssetbundleName": "lottery_game\/new_year_2022_material",
    "omikujiCoverAssetbundleName": "lottery_game\/new_year_2022_material",
    "unitFilePath": "bird_MORE MORE JUMP",
    "fortuneFilePath": "unsei_suekichi",
    "omikujiCoverFilePath": "omikuji_MORE MORE JUMP"
  },
  {
    "id": 20,
    "omikujiGroupId": 1,
    "unit": "idol",
    "fortuneType": "misfortune",
    "summary": "你可能会面临意外的灾难，\n应当彻底做好安全检查。",
    "title1": "愿望",
    "description1": "借助他人之力\n方为明智之举。",
    "title2": "健康",
    "description2": "可能会受些轻微的伤。",
    "title3": "等候之人",
    "description3": "虽然会晚，\n 但应该会到来。",
    "unitAssetbundleName": "lottery_game\/new_year_2022_material",
    "fortuneAssetbundleName": "lottery_game\/new_year_2022_material",
    "omikujiCoverAssetbundleName": "lottery_game\/new_year_2022_material",
    "unitFilePath": "bird_MORE MORE JUMP",
    "fortuneFilePath": "unsei_kyou",
    "omikujiCoverFilePath": "omikuji_MORE MORE JUMP"
  },
  {
    "id": 21,
    "omikujiGroupId": 1,
    "unit": "idol",
    "fortuneType": "grate_misfortune",
    "summary": "这将是坎坷的一年，\n打破常理的灵活思维，\n是解决问题的关键。",
    "title1": "愿望",
    "description1": "前路困难。\n但只要不放弃愿望就能实现。",
    "title2": "健康",
    "description2": "没有问题。",
    "title3": "等候之人",
    "description3": "与其等待，\n 亲自前往寻找会更快。",
    "unitAssetbundleName": "lottery_game\/new_year_2022_material",
    "fortuneAssetbundleName": "lottery_game\/new_year_2022_material",
    "omikujiCoverAssetbundleName": "lottery_game\/new_year_2022_material",
    "unitFilePath": "bird_MORE MORE JUMP",
    "fortuneFilePath": "unsei_daikyou",
    "omikujiCoverFilePath": "omikuji_MORE MORE JUMP"
  },
  {
    "id": 22,
    "omikujiGroupId": 1,
    "unit": "street",
    "fortuneType": "grate_fortune",
    "summary": "这一年中\n新的环境与新的邂逅，\n将为你的人生增添色彩。",
    "title1": "愿望",
    "description1": "会出现可靠的帮手，\n将会离目标更近。",
    "title2": "健康",
    "description2": "情况很好。\n挑战新的事物会更好。",
    "title3": "等候之人",
    "description3": "应该很快就会到来。",
    "unitAssetbundleName": "lottery_game\/new_year_2022_material",
    "fortuneAssetbundleName": "lottery_game\/new_year_2022_material",
    "omikujiCoverAssetbundleName": "lottery_game\/new_year_2022_material",
    "unitFilePath": "bird_Vivid BAD SQUAD",
    "fortuneFilePath": "unsei_daikichi",
    "omikujiCoverFilePath": "omikuji_Vivid BAD SQUAD"
  },
  {
    "id": 23,
    "omikujiGroupId": 1,
    "unit": "street",
    "fortuneType": "fortune",
    "summary": "有迹象表明，\n你的观点能够被他人理解，\n长期的烦恼将得到解决。",
    "title1": "愿望",
    "description1": "只要传达心意愿望就会实现。",
    "title2": "健康",
    "description2": "情况良好。\n忧虑一扫而空会更好。",
    "title3": "等候之人",
    "description3": "虽然没有音讯，\n 但会到来。",
    "unitAssetbundleName": "lottery_game\/new_year_2022_material",
    "fortuneAssetbundleName": "lottery_game\/new_year_2022_material",
    "omikujiCoverAssetbundleName": "lottery_game\/new_year_2022_material",
    "unitFilePath": "bird_Vivid BAD SQUAD",
    "fortuneFilePath": "unsei_kichi",
    "omikujiCoverFilePath": "omikuji_Vivid BAD SQUAD"
  },
  {
    "id": 24,
    "omikujiGroupId": 1,
    "unit": "street",
    "fortuneType": "middle_fortune",
    "summary": "尽管你会遇到一些困难，\n但能结识\n共同追梦的伙伴。",
    "title1": "愿望",
    "description1": "尽管会耗费时间，\n但愿望应该能实现。",
    "title2": "健康",
    "description2": "情况良好。",
    "title3": "等候之人",
    "description3": "会在不经意间到来。",
    "unitAssetbundleName": "lottery_game\/new_year_2022_material",
    "fortuneAssetbundleName": "lottery_game\/new_year_2022_material",
    "omikujiCoverAssetbundleName": "lottery_game\/new_year_2022_material",
    "unitFilePath": "bird_Vivid BAD SQUAD",
    "fortuneFilePath": "unsei_cyukichi",
    "omikujiCoverFilePath": "omikuji_Vivid BAD SQUAD"
  },
  {
    "id": 25,
    "omikujiGroupId": 1,
    "unit": "street",
    "fortuneType": "small_fortune",
    "summary": "你与周围人会变得更加团结，\n不断挑战方为明智之举。",
    "title1": "愿望",
    "description1": "有迹象表明你的愿望会实现。",
    "title2": "健康",
    "description2": "没有问题。",
    "title3": "等候之人",
    "description3": "应该会到来。",
    "unitAssetbundleName": "lottery_game\/new_year_2022_material",
    "fortuneAssetbundleName": "lottery_game\/new_year_2022_material",
    "omikujiCoverAssetbundleName": "lottery_game\/new_year_2022_material",
    "unitFilePath": "bird_Vivid BAD SQUAD",
    "fortuneFilePath": "unsei_syoukichi",
    "omikujiCoverFilePath": "omikuji_Vivid BAD SQUAD"
  },
  {
    "id": 26,
    "omikujiGroupId": 1,
    "unit": "street",
    "fortuneType": "uncertain_luck",
    "summary": "有迹象表明可能会发生\n让你内心动摇的事件，\n尽早解决心中的困惑方为明智之举。",
    "title1": "愿望",
    "description1": "有志者事竟成。",
    "title2": "健康",
    "description2": "身体方面没有问题，\n重新审视自己的内心吧。",
    "title3": "等候之人",
    "description3": "应该会到来。",
    "unitAssetbundleName": "lottery_game\/new_year_2022_material",
    "fortuneAssetbundleName": "lottery_game\/new_year_2022_material",
    "omikujiCoverAssetbundleName": "lottery_game\/new_year_2022_material",
    "unitFilePath": "bird_Vivid BAD SQUAD",
    "fortuneFilePath": "unsei_suekichi",
    "omikujiCoverFilePath": "omikuji_Vivid BAD SQUAD"
  },
  {
    "id": 27,
    "omikujiGroupId": 1,
    "unit": "street",
    "fortuneType": "misfortune",
    "summary": "障碍高耸难以逾越，\n理想可能还遥不可及，\n多积累经验方为明智之举。",
    "title1": "愿望",
    "description1": "凭一己之力无法实现愿望，\n应当依赖身边的人。",
    "title2": "健康",
    "description2": "没有问题。",
    "title3": "等候之人",
    "description3": "应该会到来。",
    "unitAssetbundleName": "lottery_game\/new_year_2022_material",
    "fortuneAssetbundleName": "lottery_game\/new_year_2022_material",
    "omikujiCoverAssetbundleName": "lottery_game\/new_year_2022_material",
    "unitFilePath": "bird_Vivid BAD SQUAD",
    "fortuneFilePath": "unsei_kyou",
    "omikujiCoverFilePath": "omikuji_Vivid BAD SQUAD"
  },
  {
    "id": 28,
    "omikujiGroupId": 1,
    "unit": "street",
    "fortuneType": "grate_misfortune",
    "summary": "有迹象表明你可能会遇到意外的麻烦，\n这可能会降低人们的热情，\n需冷静处理。",
    "title1": "愿望",
    "description1": "目前应该还无法实现愿望。",
    "title2": "健康",
    "description2": "虽然没有问题，\n但要注意别吃太多零食。",
    "title3": "等候之人",
    "description3": "会晚来。",
    "unitAssetbundleName": "lottery_game\/new_year_2022_material",
    "fortuneAssetbundleName": "lottery_game\/new_year_2022_material",
    "omikujiCoverAssetbundleName": "lottery_game\/new_year_2022_material",
    "unitFilePath": "bird_Vivid BAD SQUAD",
    "fortuneFilePath": "unsei_daikyou",
    "omikujiCoverFilePath": "omikuji_Vivid BAD SQUAD"
  },
  {
    "id": 29,
    "omikujiGroupId": 1,
    "unit": "theme_park",
    "fortuneType": "grate_fortune",
    "summary": "这一年中\n许多事物会出现转机，\n应当按照自身想法行动。",
    "title1": "愿望",
    "description1": "会有朋友相助，\n愿望一定能够实现。",
    "title2": "健康",
    "description2": "没有问题。",
    "title3": "等候之人",
    "description3": "一定会到来。",
    "unitAssetbundleName": "lottery_game\/new_year_2022_material",
    "fortuneAssetbundleName": "lottery_game\/new_year_2022_material",
    "omikujiCoverAssetbundleName": "lottery_game\/new_year_2022_material",
    "unitFilePath": "bird_Wonderlands×Showtime",
    "fortuneFilePath": "unsei_daikichi",
    "omikujiCoverFilePath": "omikuji_Wonderlands×Showtime"
  },
  {
    "id": 30,
    "omikujiGroupId": 1,
    "unit": "theme_park",
    "fortuneType": "fortune",
    "summary": "有迹象表明你可能会得到\n之前放弃的东西。不要犹豫，\n努力争取方为明智之举。",
    "title1": "愿望",
    "description1": "愿望能够实现。",
    "title2": "健康",
    "description2": "营养不均衡，\n要注意饮食习惯。",
    "title3": "等候之人",
    "description3": "应该会到来。",
    "unitAssetbundleName": "lottery_game\/new_year_2022_material",
    "fortuneAssetbundleName": "lottery_game\/new_year_2022_material",
    "omikujiCoverAssetbundleName": "lottery_game\/new_year_2022_material",
    "unitFilePath": "bird_Wonderlands×Showtime",
    "fortuneFilePath": "unsei_kichi",
    "omikujiCoverFilePath": "omikuji_Wonderlands×Showtime"
  },
  {
    "id": 31,
    "omikujiGroupId": 1,
    "unit": "theme_park",
    "fortuneType": "middle_fortune",
    "summary": "面对困难时，\n与伙伴商量\n是解决问题的关键。",
    "title1": "愿望",
    "description1": "会出现帮手，\n愿望能够实现。",
    "title2": "健康",
    "description2": "情况良好。",
    "title3": "等候之人",
    "description3": "会晚一些到来。",
    "unitAssetbundleName": "lottery_game\/new_year_2022_material",
    "fortuneAssetbundleName": "lottery_game\/new_year_2022_material",
    "omikujiCoverAssetbundleName": "lottery_game\/new_year_2022_material",
    "unitFilePath": "bird_Wonderlands×Showtime",
    "fortuneFilePath": "unsei_cyukichi",
    "omikujiCoverFilePath": "omikuji_Wonderlands×Showtime"
  },
  {
    "id": 32,
    "omikujiGroupId": 1,
    "unit": "theme_park",
    "fortuneType": "small_fortune",
    "summary": "与其依赖外界环境，\n不如信赖自己的能力，\n这将是更佳的选择。",
    "title1": "愿望",
    "description1": "会因意想不到的帮助而实现愿望。",
    "title2": "健康",
    "description2": "没有问题。",
    "title3": "等候之人",
    "description3": "会晚一些到来。",
    "unitAssetbundleName": "lottery_game\/new_year_2022_material",
    "fortuneAssetbundleName": "lottery_game\/new_year_2022_material",
    "omikujiCoverAssetbundleName": "lottery_game\/new_year_2022_material",
    "unitFilePath": "bird_Wonderlands×Showtime",
    "fortuneFilePath": "unsei_syoukichi",
    "omikujiCoverFilePath": "omikuji_Wonderlands×Showtime"
  },
  {
    "id": 33,
    "omikujiGroupId": 1,
    "unit": "theme_park",
    "fortuneType": "uncertain_luck",
    "summary": "起初支持你的人可能很少，\n但逐渐会变得越来越多。",
    "title1": "愿望",
    "description1": "虽然愿望现在还无法实现，\n但只要努力就会迎来转机。",
    "title2": "健康",
    "description2": "可能会遇到\n让你稍感疲惫的事。",
    "title3": "等候之人",
    "description3": "一定会到来。",
    "unitAssetbundleName": "lottery_game\/new_year_2022_material",
    "fortuneAssetbundleName": "lottery_game\/new_year_2022_material",
    "omikujiCoverAssetbundleName": "lottery_game\/new_year_2022_material",
    "unitFilePath": "bird_Wonderlands×Showtime",
    "fortuneFilePath": "unsei_suekichi",
    "omikujiCoverFilePath": "omikuji_Wonderlands×Showtime"
  },
  {
    "id": 34,
    "omikujiGroupId": 1,
    "unit": "theme_park",
    "fortuneType": "misfortune",
    "summary": "有迹象表明在关键时刻\n你可能会遭遇麻烦，\n需多加注意。",
    "title1": "愿望",
    "description1": "以现状来看愿望应该无法实现。",
    "title2": "健康",
    "description2": "要小心受伤。",
    "title3": "等候之人",
    "description3": "不久后就会到来。",
    "unitAssetbundleName": "lottery_game\/new_year_2022_material",
    "fortuneAssetbundleName": "lottery_game\/new_year_2022_material",
    "omikujiCoverAssetbundleName": "lottery_game\/new_year_2022_material",
    "unitFilePath": "bird_Wonderlands×Showtime",
    "fortuneFilePath": "unsei_kyou",
    "omikujiCoverFilePath": "omikuji_Wonderlands×Showtime"
  },
  {
    "id": 35,
    "omikujiGroupId": 1,
    "unit": "theme_park",
    "fortuneType": "grate_misfortune",
    "summary": "这一年中你会遇到很多纠纷，\n体贴他人并坚持初心\n方为明智之举。",
    "title1": "愿望",
    "description1": "凭一己之力愿望无法实现，\n应当听从周围人的建议。",
    "title2": "健康",
    "description2": "会有饮食方面的问题。\n需要注意。",
    "title3": "等候之人",
    "description3": "不会到来。\n 应当亲自创造邂逅良机。",
    "unitAssetbundleName": "lottery_game\/new_year_2022_material",
    "fortuneAssetbundleName": "lottery_game\/new_year_2022_material",
    "omikujiCoverAssetbundleName": "lottery_game\/new_year_2022_material",
    "unitFilePath": "bird_Wonderlands×Showtime",
    "fortuneFilePath": "unsei_daikyou",
    "omikujiCoverFilePath": "omikuji_Wonderlands×Showtime"
  },
  {
    "id": 36,
    "omikujiGroupId": 1,
    "unit": "school_refusal",
    "fortuneType": "grate_fortune",
    "summary": "尽管会遇到难题，\n但只要不放弃，\n忧虑便必然会得到解决。",
    "title1": "愿望",
    "description1": "愿望能够实现。\n需不言放弃，努力修行。",
    "title2": "健康",
    "description2": "要少吃零食。",
    "title3": "等候之人",
    "description3": "一定会到来。",
    "unitAssetbundleName": "lottery_game\/new_year_2022_material",
    "fortuneAssetbundleName": "lottery_game\/new_year_2022_material",
    "omikujiCoverAssetbundleName": "lottery_game\/new_year_2022_material",
    "unitFilePath": "bird_Nightcord at 25_00",
    "fortuneFilePath": "unsei_daikichi",
    "omikujiCoverFilePath": "omikuji_Nightcord at 25_00"
  },
  {
    "id": 37,
    "omikujiGroupId": 1,
    "unit": "school_refusal",
    "fortuneType": "fortune",
    "summary": "尽管你会因巨大的阻碍\n而烦恼，但跨越后\n会得到相应的成果。",
    "title1": "愿望",
    "description1": "若能获得前人的帮助，\n愿望就能实现。",
    "title2": "健康",
    "description2": "要注意饮食均衡。",
    "title3": "等候之人",
    "description3": "应该暂时不会到来。",
    "unitAssetbundleName": "lottery_game\/new_year_2022_material",
    "fortuneAssetbundleName": "lottery_game\/new_year_2022_material",
    "omikujiCoverAssetbundleName": "lottery_game\/new_year_2022_material",
    "unitFilePath": "bird_Nightcord at 25_00",
    "fortuneFilePath": "unsei_kichi",
    "omikujiCoverFilePath": "omikuji_Nightcord at 25_00"
  },
  {
    "id": 38,
    "omikujiGroupId": 1,
    "unit": "school_refusal",
    "fortuneType": "middle_fortune",
    "summary": "你将能顺利胜任各种角色。",
    "title1": "愿望",
    "description1": "愿望能够实现。",
    "title2": "健康",
    "description2": "不要忽视睡眠。",
    "title3": "等候之人",
    "description3": "应该会稍晚一些到来。",
    "unitAssetbundleName": "lottery_game\/new_year_2022_material",
    "fortuneAssetbundleName": "lottery_game\/new_year_2022_material",
    "omikujiCoverAssetbundleName": "lottery_game\/new_year_2022_material",
    "unitFilePath": "bird_Nightcord at 25_00",
    "fortuneFilePath": "unsei_cyukichi",
    "omikujiCoverFilePath": "omikuji_Nightcord at 25_00"
  },
  {
    "id": 39,
    "omikujiGroupId": 1,
    "unit": "school_refusal",
    "fortuneType": "small_fortune",
    "summary": "这一年中\n尽管遇到的都是小事，\n也将引起你内心的转变。",
    "title1": "愿望",
    "description1": "只要耐心等待，\n愿望就能实现。",
    "title2": "健康",
    "description2": "虽然没有问题，\n但不能勉强自己。",
    "title3": "等候之人",
    "description3": "应该会顺利到来。",
    "unitAssetbundleName": "lottery_game\/new_year_2022_material",
    "fortuneAssetbundleName": "lottery_game\/new_year_2022_material",
    "omikujiCoverAssetbundleName": "lottery_game\/new_year_2022_material",
    "unitFilePath": "bird_Nightcord at 25_00",
    "fortuneFilePath": "unsei_syoukichi",
    "omikujiCoverFilePath": "omikuji_Nightcord at 25_00"
  },
  {
    "id": 40,
    "omikujiGroupId": 1,
    "unit": "school_refusal",
    "fortuneType": "uncertain_luck",
    "summary": "若能偶尔转换心情，\n接触外面的世界，\n你便能得到新的启发。",
    "title1": "愿望",
    "description1": "愿望会在不经意间实现。",
    "title2": "健康",
    "description2": "基本上没有问题，\n需要多加运动。",
    "title3": "等候之人",
    "description3": "虽然没有音讯，\n 但会到来。",
    "unitAssetbundleName": "lottery_game\/new_year_2022_material",
    "fortuneAssetbundleName": "lottery_game\/new_year_2022_material",
    "omikujiCoverAssetbundleName": "lottery_game\/new_year_2022_material",
    "unitFilePath": "bird_Nightcord at 25_00",
    "fortuneFilePath": "unsei_suekichi",
    "omikujiCoverFilePath": "omikuji_Nightcord at 25_00"
  },
  {
    "id": 41,
    "omikujiGroupId": 1,
    "unit": "school_refusal",
    "fortuneType": "misfortune",
    "summary": "你将面临进退抉择，\n若心有迷茫，\n也可决定不做选择。",
    "title1": "愿望",
    "description1": "愿望实现不会如期而至。",
    "title2": "健康",
    "description2": "有迹象表明你感到心力交瘁。",
    "title3": "等候之人",
    "description3": "只要心怀祈愿，\n 就会到来。",
    "unitAssetbundleName": "lottery_game\/new_year_2022_material",
    "fortuneAssetbundleName": "lottery_game\/new_year_2022_material",
    "omikujiCoverAssetbundleName": "lottery_game\/new_year_2022_material",
    "unitFilePath": "bird_Nightcord at 25_00",
    "fortuneFilePath": "unsei_kyou",
    "omikujiCoverFilePath": "omikuji_Nightcord at 25_00"
  },
  {
    "id": 42,
    "omikujiGroupId": 1,
    "unit": "school_refusal",
    "fortuneType": "grate_misfortune",
    "summary": "这一年中\n你将面临诸多困惑，\n好好审视自己的内心吧。",
    "title1": "愿望",
    "description1": "有迹象表明愿望目前还无法实现，\n但只要坚持不懈终将实现。",
    "title2": "健康",
    "description2": "很可能出现缺乏运动的状况。",
    "title3": "等候之人",
    "description3": "应该会到来。",
    "unitAssetbundleName": "lottery_game\/new_year_2022_material",
    "fortuneAssetbundleName": "lottery_game\/new_year_2022_material",
    "omikujiCoverAssetbundleName": "lottery_game\/new_year_2022_material",
    "unitFilePath": "bird_Nightcord at 25_00",
    "fortuneFilePath": "unsei_daikyou",
    "omikujiCoverFilePath": "omikuji_Nightcord at 25_00"
  },
  {
    "id": 43,
    "omikujiGroupId": 2,
    "unit": "piapro",
    "fortuneType": "grate_fortune",
    "summary": "若持续祈愿，\n所孕育的事物，\n便会在今年开花结果。",
    "title1": "愿望",
    "description1": "愿望定将实现。",
    "title2": "健康",
    "description2": "情况非常好。",
    "title3": "等候之人",
    "description3": "一定会到来。",
    "unitAssetbundleName": "lottery_game\/new_year_2023_material",
    "fortuneAssetbundleName": "lottery_game\/new_year_2023_material",
    "omikujiCoverAssetbundleName": "lottery_game\/new_year_2023_material",
    "unitFilePath": "bird_VIRTUAL SINGER",
    "fortuneFilePath": "unsei_daikichi",
    "omikujiCoverFilePath": "omikuji_VIRTUAL SINGER"
  },
  {
    "id": 44,
    "omikujiGroupId": 2,
    "unit": "piapro",
    "fortuneType": "fortune",
    "summary": "若助人为乐，\n今年就会更加美好。",
    "title1": "愿望",
    "description1": "愿望能够实现。",
    "title2": "健康",
    "description2": "情况良好。",
    "title3": "等候之人",
    "description3": "会到来。\n 且有音讯。",
    "unitAssetbundleName": "lottery_game\/new_year_2023_material",
    "fortuneAssetbundleName": "lottery_game\/new_year_2023_material",
    "omikujiCoverAssetbundleName": "lottery_game\/new_year_2023_material",
    "unitFilePath": "bird_VIRTUAL SINGER",
    "fortuneFilePath": "unsei_kichi",
    "omikujiCoverFilePath": "omikuji_VIRTUAL SINGER"
  },
  {
    "id": 45,
    "omikujiGroupId": 2,
    "unit": "piapro",
    "fortuneType": "middle_fortune",
    "summary": "你的言行可能会在\n不经意间帮到他人，\n按照自己的想法行动吧。",
    "title1": "愿望",
    "description1": "愿望应该能够实现。",
    "title2": "健康",
    "description2": "情况良好。",
    "title3": "等候之人",
    "description3": "虽然暂时没有音讯，\n 但会到来。",
    "unitAssetbundleName": "lottery_game\/new_year_2023_material",
    "fortuneAssetbundleName": "lottery_game\/new_year_2023_material",
    "omikujiCoverAssetbundleName": "lottery_game\/new_year_2023_material",
    "unitFilePath": "bird_VIRTUAL SINGER",
    "fortuneFilePath": "unsei_cyukichi",
    "omikujiCoverFilePath": "omikuji_VIRTUAL SINGER"
  },
  {
    "id": 46,
    "omikujiGroupId": 2,
    "unit": "piapro",
    "fortuneType": "small_fortune",
    "summary": "你的经验\n可能会帮到他人，\n主动伸出援手吧。",
    "title1": "愿望",
    "description1": "若付出努力，愿望应该就能实现。",
    "title2": "健康",
    "description2": "少吃甜食。",
    "title3": "等候之人",
    "description3": "会有音讯。",
    "unitAssetbundleName": "lottery_game\/new_year_2023_material",
    "fortuneAssetbundleName": "lottery_game\/new_year_2023_material",
    "omikujiCoverAssetbundleName": "lottery_game\/new_year_2023_material",
    "unitFilePath": "bird_VIRTUAL SINGER",
    "fortuneFilePath": "unsei_syoukichi",
    "omikujiCoverFilePath": "omikuji_VIRTUAL SINGER"
  },
  {
    "id": 47,
    "omikujiGroupId": 2,
    "unit": "piapro",
    "fortuneType": "uncertain_luck",
    "summary": "尽管这一年充满坎坷，\n但只要心志坚定，\n你就能转化为机遇。",
    "title1": "愿望",
    "description1": "尽管会遇到困难，\n但愿望应该能够实现。",
    "title2": "健康",
    "description2": "情况良好。",
    "title3": "等候之人",
    "description3": "会晚来。",
    "unitAssetbundleName": "lottery_game\/new_year_2023_material",
    "fortuneAssetbundleName": "lottery_game\/new_year_2023_material",
    "omikujiCoverAssetbundleName": "lottery_game\/new_year_2023_material",
    "unitFilePath": "bird_VIRTUAL SINGER",
    "fortuneFilePath": "unsei_suekichi",
    "omikujiCoverFilePath": "omikuji_VIRTUAL SINGER"
  },
  {
    "id": 48,
    "omikujiGroupId": 2,
    "unit": "piapro",
    "fortuneType": "misfortune",
    "summary": "有迹象表明\n你的言行会招致麻烦，\n应当积极采纳他人的建议。",
    "title1": "愿望",
    "description1": "不要着急，静待良机。",
    "title2": "健康",
    "description2": "要适度运动。",
    "title3": "等候之人",
    "description3": "应当亲自创造邂逅良机。",
    "unitAssetbundleName": "lottery_game\/new_year_2023_material",
    "fortuneAssetbundleName": "lottery_game\/new_year_2023_material",
    "omikujiCoverAssetbundleName": "lottery_game\/new_year_2023_material",
    "unitFilePath": "bird_VIRTUAL SINGER",
    "fortuneFilePath": "unsei_kyou",
    "omikujiCoverFilePath": "omikuji_VIRTUAL SINGER"
  },
  {
    "id": 49,
    "omikujiGroupId": 2,
    "unit": "piapro",
    "fortuneType": "grate_misfortune",
    "summary": "有迹象表明\n你会因不顺之事感到心情郁闷，\n去寻求他人的帮助吧。",
    "title1": "愿望",
    "description1": "若维持现状，愿望无法实现。",
    "title2": "健康",
    "description2": "身心都不太稳定，\n需多加留意。",
    "title3": "等候之人",
    "description3": "不会到来。",
    "unitAssetbundleName": "lottery_game\/new_year_2023_material",
    "fortuneAssetbundleName": "lottery_game\/new_year_2023_material",
    "omikujiCoverAssetbundleName": "lottery_game\/new_year_2023_material",
    "unitFilePath": "bird_VIRTUAL SINGER",
    "fortuneFilePath": "unsei_daikyou",
    "omikujiCoverFilePath": "omikuji_VIRTUAL SINGER"
  },
  {
    "id": 50,
    "omikujiGroupId": 2,
    "unit": "light_sound",
    "fortuneType": "grate_fortune",
    "summary": "有迹象表明\n你之前的积累将会结出硕果，\n应该继续努力。",
    "title1": "愿望",
    "description1": "若下定决心，\n愿望就能够实现。",
    "title2": "健康",
    "description2": "情况非常好。",
    "title3": "等候之人",
    "description3": "一定会到来。",
    "unitAssetbundleName": "lottery_game\/new_year_2023_material",
    "fortuneAssetbundleName": "lottery_game\/new_year_2023_material",
    "omikujiCoverAssetbundleName": "lottery_game\/new_year_2023_material",
    "unitFilePath": "bird_Leoneed",
    "fortuneFilePath": "unsei_daikichi",
    "omikujiCoverFilePath": "omikuji_Leoneed"
  },
  {
    "id": 51,
    "omikujiGroupId": 2,
    "unit": "light_sound",
    "fortuneType": "fortune",
    "summary": "这一年中\n你会因环境变化感到困惑，\n行分内之事便能克服障碍。",
    "title1": "愿望",
    "description1": "与伙伴齐心协力，\n愿望就能实现。",
    "title2": "健康",
    "description2": "情况良好。",
    "title3": "等候之人",
    "description3": "会到来。",
    "unitAssetbundleName": "lottery_game\/new_year_2023_material",
    "fortuneAssetbundleName": "lottery_game\/new_year_2023_material",
    "omikujiCoverAssetbundleName": "lottery_game\/new_year_2023_material",
    "unitFilePath": "bird_Leoneed",
    "fortuneFilePath": "unsei_kichi",
    "omikujiCoverFilePath": "omikuji_Leoneed"
  },
  {
    "id": 52,
    "omikujiGroupId": 2,
    "unit": "light_sound",
    "fortuneType": "middle_fortune",
    "summary": "正视过去，\n这是解决问题的关键。",
    "title1": "愿望",
    "description1": "大胆表现愿望就能实现。",
    "title2": "健康",
    "description2": "不能勉强自己。",
    "title3": "等候之人",
    "description3": "会晚来。",
    "unitAssetbundleName": "lottery_game\/new_year_2023_material",
    "fortuneAssetbundleName": "lottery_game\/new_year_2023_material",
    "omikujiCoverAssetbundleName": "lottery_game\/new_year_2023_material",
    "unitFilePath": "bird_Leoneed",
    "fortuneFilePath": "unsei_cyukichi",
    "omikujiCoverFilePath": "omikuji_Leoneed"
  },
  {
    "id": 53,
    "omikujiGroupId": 2,
    "unit": "light_sound",
    "fortuneType": "small_fortune",
    "summary": "就算进展不顺利，\n只要不放弃，\n前进之路自然会为你敞开。",
    "title1": "愿望",
    "description1": "仰赖前人愿望就能实现。",
    "title2": "健康",
    "description2": "要注意饮食均衡。",
    "title3": "等候之人",
    "description3": "应当亲自创造邂逅良机。",
    "unitAssetbundleName": "lottery_game\/new_year_2023_material",
    "fortuneAssetbundleName": "lottery_game\/new_year_2023_material",
    "omikujiCoverAssetbundleName": "lottery_game\/new_year_2023_material",
    "unitFilePath": "bird_Leoneed",
    "fortuneFilePath": "unsei_syoukichi",
    "omikujiCoverFilePath": "omikuji_Leoneed"
  },
  {
    "id": 54,
    "omikujiGroupId": 2,
    "unit": "light_sound",
    "fortuneType": "uncertain_luck",
    "summary": "你可能会因\n事与愿违而烦恼。",
    "title1": "愿望",
    "description1": "只要坚持下去，\n前进的道路就会开启。",
    "title2": "健康",
    "description2": "有迹象表明你感到心力交瘁。",
    "title3": "等候之人",
    "description3": "会到来。",
    "unitAssetbundleName": "lottery_game\/new_year_2023_material",
    "fortuneAssetbundleName": "lottery_game\/new_year_2023_material",
    "omikujiCoverAssetbundleName": "lottery_game\/new_year_2023_material",
    "unitFilePath": "bird_Leoneed",
    "fortuneFilePath": "unsei_suekichi",
    "omikujiCoverFilePath": "omikuji_Leoneed"
  },
  {
    "id": 55,
    "omikujiGroupId": 2,
    "unit": "light_sound",
    "fortuneType": "misfortune",
    "summary": "这一年中\n你的言行可能招致误会，\n发言前需慎重考虑。",
    "title1": "愿望",
    "description1": "愿望现在还无法实现。",
    "title2": "健康",
    "description2": "没有问题。",
    "title3": "等候之人",
    "description3": "会晚来。",
    "unitAssetbundleName": "lottery_game\/new_year_2023_material",
    "fortuneAssetbundleName": "lottery_game\/new_year_2023_material",
    "omikujiCoverAssetbundleName": "lottery_game\/new_year_2023_material",
    "unitFilePath": "bird_Leoneed",
    "fortuneFilePath": "unsei_kyou",
    "omikujiCoverFilePath": "omikuji_Leoneed"
  },
  {
    "id": 56,
    "omikujiGroupId": 2,
    "unit": "light_sound",
    "fortuneType": "grate_misfortune",
    "summary": "有些困难难以\n依靠自身努力解决，\n去寻求他人的帮助吧。",
    "title1": "愿望",
    "description1": "若维持现状，\n愿望很难实现。",
    "title2": "健康",
    "description2": "少吃甜食。",
    "title3": "等候之人",
    "description3": "应该会到来。",
    "unitAssetbundleName": "lottery_game\/new_year_2023_material",
    "fortuneAssetbundleName": "lottery_game\/new_year_2023_material",
    "omikujiCoverAssetbundleName": "lottery_game\/new_year_2023_material",
    "unitFilePath": "bird_Leoneed",
    "fortuneFilePath": "unsei_daikyou",
    "omikujiCoverFilePath": "omikuji_Leoneed"
  },
  {
    "id": 57,
    "omikujiGroupId": 2,
    "unit": "idol",
    "fortuneType": "grate_fortune",
    "summary": "这一年中不懈的努力\n会开花结果，你将遇到\n实现梦想的转折点。",
    "title1": "愿望",
    "description1": "万事小心愿望就能实现。",
    "title2": "健康",
    "description2": "只要坚持运动，\n身体状况就会变好。",
    "title3": "等候之人",
    "description3": "应该会到来。",
    "unitAssetbundleName": "lottery_game\/new_year_2023_material",
    "fortuneAssetbundleName": "lottery_game\/new_year_2023_material",
    "omikujiCoverAssetbundleName": "lottery_game\/new_year_2023_material",
    "unitFilePath": "bird_MORE MORE JUMP",
    "fortuneFilePath": "unsei_daikichi",
    "omikujiCoverFilePath": "omikuji_MORE MORE JUMP"
  },
  {
    "id": 58,
    "omikujiGroupId": 2,
    "unit": "idol",
    "fortuneType": "fortune",
    "summary": "这一年中你会得到许多\n与各种人交流的机会，\n享受充满活力的日常生活吧。",
    "title1": "愿望",
    "description1": "会得到朋友的帮助，\n愿望能够实现。",
    "title2": "健康",
    "description2": "甜食有助于缓解疲劳。",
    "title3": "等候之人",
    "description3": "会到来。",
    "unitAssetbundleName": "lottery_game\/new_year_2023_material",
    "fortuneAssetbundleName": "lottery_game\/new_year_2023_material",
    "omikujiCoverAssetbundleName": "lottery_game\/new_year_2023_material",
    "unitFilePath": "bird_MORE MORE JUMP",
    "fortuneFilePath": "unsei_kichi",
    "omikujiCoverFilePath": "omikuji_MORE MORE JUMP"
  },
  {
    "id": 59,
    "omikujiGroupId": 2,
    "unit": "idol",
    "fortuneType": "middle_fortune",
    "summary": "这一年中\n你会迎来重大的转机，\n需要做出大胆的决定。",
    "title1": "愿望",
    "description1": "至今的努力会得到回报，\n愿望能够实现。",
    "title2": "健康",
    "description2": "情况良好。",
    "title3": "等候之人",
    "description3": "会有音讯。",
    "unitAssetbundleName": "lottery_game\/new_year_2023_material",
    "fortuneAssetbundleName": "lottery_game\/new_year_2023_material",
    "omikujiCoverAssetbundleName": "lottery_game\/new_year_2023_material",
    "unitFilePath": "bird_MORE MORE JUMP",
    "fortuneFilePath": "unsei_cyukichi",
    "omikujiCoverFilePath": "omikuji_MORE MORE JUMP"
  },
  {
    "id": 60,
    "omikujiGroupId": 2,
    "unit": "idol",
    "fortuneType": "small_fortune",
    "summary": "虽然事情可能不能\n如你所愿，但最终时间\n会解决一切。",
    "title1": "愿望",
    "description1": "一开始很难实现愿望，\n但会逐渐顺利起来。",
    "title2": "健康",
    "description2": "没有问题。",
    "title3": "等候之人",
    "description3": "不会到来。",
    "unitAssetbundleName": "lottery_game\/new_year_2023_material",
    "fortuneAssetbundleName": "lottery_game\/new_year_2023_material",
    "omikujiCoverAssetbundleName": "lottery_game\/new_year_2023_material",
    "unitFilePath": "bird_MORE MORE JUMP",
    "fortuneFilePath": "unsei_syoukichi",
    "omikujiCoverFilePath": "omikuji_MORE MORE JUMP"
  },
  {
    "id": 61,
    "omikujiGroupId": 2,
    "unit": "idol",
    "fortuneType": "uncertain_luck",
    "summary": "这一年中你会感到犹豫迷茫，\n被迫面临许多选择，\n相信自己的决定吧。",
    "title1": "愿望",
    "description1": "若维持现状，\n则愿望难以实现。",
    "title2": "健康",
    "description2": "没有问题。",
    "title3": "等候之人",
    "description3": "应该会到来。",
    "unitAssetbundleName": "lottery_game\/new_year_2023_material",
    "fortuneAssetbundleName": "lottery_game\/new_year_2023_material",
    "omikujiCoverAssetbundleName": "lottery_game\/new_year_2023_material",
    "unitFilePath": "bird_MORE MORE JUMP",
    "fortuneFilePath": "unsei_suekichi",
    "omikujiCoverFilePath": "omikuji_MORE MORE JUMP"
  },
  {
    "id": 62,
    "omikujiGroupId": 2,
    "unit": "idol",
    "fortuneType": "misfortune",
    "summary": "有迹象表明旧日的因缘或纠纷\n可能会给你造成麻烦，\n需多加留意。",
    "title1": "愿望",
    "description1": "会得到许多帮助，\n愿望应该能实现。",
    "title2": "健康",
    "description2": "没有问题。",
    "title3": "等候之人",
    "description3": "会不期而至。",
    "unitAssetbundleName": "lottery_game\/new_year_2023_material",
    "fortuneAssetbundleName": "lottery_game\/new_year_2023_material",
    "omikujiCoverAssetbundleName": "lottery_game\/new_year_2023_material",
    "unitFilePath": "bird_MORE MORE JUMP",
    "fortuneFilePath": "unsei_kyou",
    "omikujiCoverFilePath": "omikuji_MORE MORE JUMP"
  },
  {
    "id": 63,
    "omikujiGroupId": 2,
    "unit": "idol",
    "fortuneType": "grate_misfortune",
    "summary": "这一年中你会遇到\n巨大的机挑战，要有坚强的\n耐心和毅力去面对。",
    "title1": "愿望",
    "description1": "虽然愿望会实现，\n但不会完全如你所愿。",
    "title2": "健康",
    "description2": "有迹象表明你心力交瘁的\n情况很严重，请务必注意。",
    "title3": "等候之人",
    "description3": "会有音讯。",
    "unitAssetbundleName": "lottery_game\/new_year_2023_material",
    "fortuneAssetbundleName": "lottery_game\/new_year_2023_material",
    "omikujiCoverAssetbundleName": "lottery_game\/new_year_2023_material",
    "unitFilePath": "bird_MORE MORE JUMP",
    "fortuneFilePath": "unsei_daikyou",
    "omikujiCoverFilePath": "omikuji_MORE MORE JUMP"
  },
  {
    "id": 64,
    "omikujiGroupId": 2,
    "unit": "street",
    "fortuneType": "grate_fortune",
    "summary": "你离梦想又近了一步，\n将获得宝贵的经验。",
    "title1": "愿望",
    "description1": "磨练实力愿望就会实现，\n需努力修行。",
    "title2": "健康",
    "description2": "情况非常好。",
    "title3": "等候之人",
    "description3": "会到来。",
    "unitAssetbundleName": "lottery_game\/new_year_2023_material",
    "fortuneAssetbundleName": "lottery_game\/new_year_2023_material",
    "omikujiCoverAssetbundleName": "lottery_game\/new_year_2023_material",
    "unitFilePath": "bird_Vivid BAD SQUAD",
    "fortuneFilePath": "unsei_daikichi",
    "omikujiCoverFilePath": "omikuji_Vivid BAD SQUAD"
  },
  {
    "id": 65,
    "omikujiGroupId": 2,
    "unit": "street",
    "fortuneType": "fortune",
    "summary": "你会找到一种与人交往时，\n充分发挥才能的方法。",
    "title1": "愿望",
    "description1": "会得到前人的指导，\n愿望应该能够实现。",
    "title2": "健康",
    "description2": "情况良好。",
    "title3": "等候之人",
    "description3": "会到来。",
    "unitAssetbundleName": "lottery_game\/new_year_2023_material",
    "fortuneAssetbundleName": "lottery_game\/new_year_2023_material",
    "omikujiCoverAssetbundleName": "lottery_game\/new_year_2023_material",
    "unitFilePath": "bird_Vivid BAD SQUAD",
    "fortuneFilePath": "unsei_kichi",
    "omikujiCoverFilePath": "omikuji_Vivid BAD SQUAD"
  },
  {
    "id": 66,
    "omikujiGroupId": 2,
    "unit": "street",
    "fortuneType": "middle_fortune",
    "summary": "这一年中你会更加\n关注你的梦想与希望，\n需继续努力。",
    "title1": "愿望",
    "description1": "只要强烈期待，\n愿望应该就能实现。",
    "title2": "健康",
    "description2": "情况良好。",
    "title3": "等候之人",
    "description3": "会不期而至。",
    "unitAssetbundleName": "lottery_game\/new_year_2023_material",
    "fortuneAssetbundleName": "lottery_game\/new_year_2023_material",
    "omikujiCoverAssetbundleName": "lottery_game\/new_year_2023_material",
    "unitFilePath": "bird_Vivid BAD SQUAD",
    "fortuneFilePath": "unsei_cyukichi",
    "omikujiCoverFilePath": "omikuji_Vivid BAD SQUAD"
  },
  {
    "id": 67,
    "omikujiGroupId": 2,
    "unit": "street",
    "fortuneType": "small_fortune",
    "summary": "有迹象表明你会因\n意外之事而摇摆不定，\n需坚定自己的意志。",
    "title1": "愿望",
    "description1": "与旁人商量愿望就会实现，\n应当重视与伙伴的交流。",
    "title2": "健康",
    "description2": "可能会感到心力交瘁。",
    "title3": "等候之人",
    "description3": "应该很快就会到来。",
    "unitAssetbundleName": "lottery_game\/new_year_2023_material",
    "fortuneAssetbundleName": "lottery_game\/new_year_2023_material",
    "omikujiCoverAssetbundleName": "lottery_game\/new_year_2023_material",
    "unitFilePath": "bird_Vivid BAD SQUAD",
    "fortuneFilePath": "unsei_syoukichi",
    "omikujiCoverFilePath": "omikuji_Vivid BAD SQUAD"
  },
  {
    "id": 68,
    "omikujiGroupId": 2,
    "unit": "street",
    "fortuneType": "uncertain_luck",
    "summary": "你将有机会斩断过去的因缘，\n一旦跨过这一步，\n便前途无量。",
    "title1": "愿望",
    "description1": "只要拥有坚强的意志，\n愿望就会实现。",
    "title2": "健康",
    "description2": "情况非常好。\n建议坚持运动。",
    "title3": "等候之人",
    "description3": "应该会到来。",
    "unitAssetbundleName": "lottery_game\/new_year_2023_material",
    "fortuneAssetbundleName": "lottery_game\/new_year_2023_material",
    "omikujiCoverAssetbundleName": "lottery_game\/new_year_2023_material",
    "unitFilePath": "bird_Vivid BAD SQUAD",
    "fortuneFilePath": "unsei_suekichi",
    "omikujiCoverFilePath": "omikuji_Vivid BAD SQUAD"
  },
  {
    "id": 69,
    "omikujiGroupId": 2,
    "unit": "street",
    "fortuneType": "misfortune",
    "summary": "有迹象表明\n不顺心的事情可能会\n接踵而至。",
    "title1": "愿望",
    "description1": "愿望应该很难实现。",
    "title2": "健康",
    "description2": "没有问题。",
    "title3": "等候之人",
    "description3": "虽然会到来，\n 但不会很快。",
    "unitAssetbundleName": "lottery_game\/new_year_2023_material",
    "fortuneAssetbundleName": "lottery_game\/new_year_2023_material",
    "omikujiCoverAssetbundleName": "lottery_game\/new_year_2023_material",
    "unitFilePath": "bird_Vivid BAD SQUAD",
    "fortuneFilePath": "unsei_kyou",
    "omikujiCoverFilePath": "omikuji_Vivid BAD SQUAD"
  },
  {
    "id": 70,
    "omikujiGroupId": 2,
    "unit": "street",
    "fortuneType": "grate_misfortune",
    "summary": "有迹象表明你会因为自己\n不如周围的人而感到自卑。\n继续努力不要放弃。",
    "title1": "愿望",
    "description1": "愿望距离实现还很遥远，\n但只要努力就会有所进展。",
    "title2": "健康",
    "description2": "没有问题。",
    "title3": "等候之人",
    "description3": "会晚来。",
    "unitAssetbundleName": "lottery_game\/new_year_2023_material",
    "fortuneAssetbundleName": "lottery_game\/new_year_2023_material",
    "omikujiCoverAssetbundleName": "lottery_game\/new_year_2023_material",
    "unitFilePath": "bird_Vivid BAD SQUAD",
    "fortuneFilePath": "unsei_daikyou",
    "omikujiCoverFilePath": "omikuji_Vivid BAD SQUAD"
  },
  {
    "id": 71,
    "omikujiGroupId": 2,
    "unit": "theme_park",
    "fortuneType": "grate_fortune",
    "summary": "这一年中你会通过各种经历，\n朝梦想大步迈进。",
    "title1": "愿望",
    "description1": "愿望应该能够实现。",
    "title2": "健康",
    "description2": "情况非常好。",
    "title3": "等候之人",
    "description3": "一定会到来。",
    "unitAssetbundleName": "lottery_game\/new_year_2023_material",
    "fortuneAssetbundleName": "lottery_game\/new_year_2023_material",
    "omikujiCoverAssetbundleName": "lottery_game\/new_year_2023_material",
    "unitFilePath": "bird_Wonderlands×Showtime",
    "fortuneFilePath": "unsei_daikichi",
    "omikujiCoverFilePath": "omikuji_Wonderlands×Showtime"
  },
  {
    "id": 72,
    "omikujiGroupId": 2,
    "unit": "theme_park",
    "fortuneType": "fortune",
    "summary": "这一年中你会克服自身障碍\n得到成长，过去的经验是\n解决问题的关键。",
    "title1": "愿望",
    "description1": "有努力相伴，\n愿望就一定能实现。",
    "title2": "健康",
    "description2": "情况良好。",
    "title3": "等候之人",
    "description3": "一定会到来。",
    "unitAssetbundleName": "lottery_game\/new_year_2023_material",
    "fortuneAssetbundleName": "lottery_game\/new_year_2023_material",
    "omikujiCoverAssetbundleName": "lottery_game\/new_year_2023_material",
    "unitFilePath": "bird_Wonderlands×Showtime",
    "fortuneFilePath": "unsei_kichi",
    "omikujiCoverFilePath": "omikuji_Wonderlands×Showtime"
  },
  {
    "id": 73,
    "omikujiGroupId": 2,
    "unit": "theme_park",
    "fortuneType": "middle_fortune",
    "summary": "遇事不决时，唯有坚定\n自己的信念为梦想全力以赴\n才是捷径。",
    "title1": "愿望",
    "description1": "在伙伴们的帮助下\n愿望能够实现。",
    "title2": "健康",
    "description2": "情况良好。",
    "title3": "等候之人",
    "description3": "会到来。",
    "unitAssetbundleName": "lottery_game\/new_year_2023_material",
    "fortuneAssetbundleName": "lottery_game\/new_year_2023_material",
    "omikujiCoverAssetbundleName": "lottery_game\/new_year_2023_material",
    "unitFilePath": "bird_Wonderlands×Showtime",
    "fortuneFilePath": "unsei_cyukichi",
    "omikujiCoverFilePath": "omikuji_Wonderlands×Showtime"
  },
  {
    "id": 74,
    "omikujiGroupId": 2,
    "unit": "theme_park",
    "fortuneType": "small_fortune",
    "summary": "即使遇到困难，只要\n勇于挑战，你就能获得\n显著的成长和进步。",
    "title1": "愿望",
    "description1": "持续努力，\n应该就会看见希望。",
    "title2": "健康",
    "description2": "有受伤的可能性。",
    "title3": "等候之人",
    "description3": "会晚来。",
    "unitAssetbundleName": "lottery_game\/new_year_2023_material",
    "fortuneAssetbundleName": "lottery_game\/new_year_2023_material",
    "omikujiCoverAssetbundleName": "lottery_game\/new_year_2023_material",
    "unitFilePath": "bird_Wonderlands×Showtime",
    "fortuneFilePath": "unsei_syoukichi",
    "omikujiCoverFilePath": "omikuji_Wonderlands×Showtime"
  },
  {
    "id": 75,
    "omikujiGroupId": 2,
    "unit": "theme_park",
    "fortuneType": "uncertain_luck",
    "summary": "这一年中你会关注自己的心愿，\n在感到迷茫无措时，\n聆听内心的声音是明智之举。",
    "title1": "愿望",
    "description1": "会找到实现愿望之路。",
    "title2": "健康",
    "description2": "没有问题。",
    "title3": "等候之人",
    "description3": "会到来。",
    "unitAssetbundleName": "lottery_game\/new_year_2023_material",
    "fortuneAssetbundleName": "lottery_game\/new_year_2023_material",
    "omikujiCoverAssetbundleName": "lottery_game\/new_year_2023_material",
    "unitFilePath": "bird_Wonderlands×Showtime",
    "fortuneFilePath": "unsei_suekichi",
    "omikujiCoverFilePath": "omikuji_Wonderlands×Showtime"
  },
  {
    "id": 76,
    "omikujiGroupId": 2,
    "unit": "theme_park",
    "fortuneType": "misfortune",
    "summary": "切勿仓促行动，\n应当先面对眼前的事物。",
    "title1": "愿望",
    "description1": "还需要努力。",
    "title2": "健康",
    "description2": "有迹象表明你心慌意乱。",
    "title3": "等候之人",
    "description3": "应当亲自创造邂逅良机。",
    "unitAssetbundleName": "lottery_game\/new_year_2023_material",
    "fortuneAssetbundleName": "lottery_game\/new_year_2023_material",
    "omikujiCoverAssetbundleName": "lottery_game\/new_year_2023_material",
    "unitFilePath": "bird_Wonderlands×Showtime",
    "fortuneFilePath": "unsei_kyou",
    "omikujiCoverFilePath": "omikuji_Wonderlands×Showtime"
  },
  {
    "id": 77,
    "omikujiGroupId": 2,
    "unit": "theme_park",
    "fortuneType": "grate_misfortune",
    "summary": "你可能会遭遇\n意想不到的事故，\n出行时要多加注意。",
    "title1": "愿望",
    "description1": "愿望现在还无法实现。",
    "title2": "健康",
    "description2": "要增强基础体力。",
    "title3": "等候之人",
    "description3": "虽然会到来，\n 但不会很快。",
    "unitAssetbundleName": "lottery_game\/new_year_2023_material",
    "fortuneAssetbundleName": "lottery_game\/new_year_2023_material",
    "omikujiCoverAssetbundleName": "lottery_game\/new_year_2023_material",
    "unitFilePath": "bird_Wonderlands×Showtime",
    "fortuneFilePath": "unsei_daikyou",
    "omikujiCoverFilePath": "omikuji_Wonderlands×Showtime"
  },
  {
    "id": 78,
    "omikujiGroupId": 2,
    "unit": "school_refusal",
    "fortuneType": "grate_fortune",
    "summary": "这一年中将会充满机遇，\n你同各种人相遇交流，\n带来新的转机。",
    "title1": "愿望",
    "description1": "付出努力愿望就能实现。",
    "title2": "健康",
    "description2": "情况良好。",
    "title3": "等候之人",
    "description3": "一定会到来。",
    "unitAssetbundleName": "lottery_game\/new_year_2023_material",
    "fortuneAssetbundleName": "lottery_game\/new_year_2023_material",
    "omikujiCoverAssetbundleName": "lottery_game\/new_year_2023_material",
    "unitFilePath": "bird_Nightcord at 25_00",
    "fortuneFilePath": "unsei_daikichi",
    "omikujiCoverFilePath": "omikuji_Nightcord at 25_00"
  },
  {
    "id": 79,
    "omikujiGroupId": 2,
    "unit": "school_refusal",
    "fortuneType": "fortune",
    "summary": "即使你现在很艰苦，\n但终有一天你能找到\n舒适的容身之处。",
    "title1": "愿望",
    "description1": "愿望应该能够实现。",
    "title2": "健康",
    "description2": "没有问题。",
    "title3": "等候之人",
    "description3": "会到来。",
    "unitAssetbundleName": "lottery_game\/new_year_2023_material",
    "fortuneAssetbundleName": "lottery_game\/new_year_2023_material",
    "omikujiCoverAssetbundleName": "lottery_game\/new_year_2023_material",
    "unitFilePath": "bird_Nightcord at 25_00",
    "fortuneFilePath": "unsei_kichi",
    "omikujiCoverFilePath": "omikuji_Nightcord at 25_00"
  },
  {
    "id": 80,
    "omikujiGroupId": 2,
    "unit": "school_refusal",
    "fortuneType": "middle_fortune",
    "summary": "你将通过他人获得\n许多相遇交流的机会，\n多出去走走吧。",
    "title1": "愿望",
    "description1": "会得到他人的帮助，\n实现愿望。",
    "title2": "健康",
    "description2": "要转换一下心情。",
    "title3": "等候之人",
    "description3": "会在不经意间相逢。",
    "unitAssetbundleName": "lottery_game\/new_year_2023_material",
    "fortuneAssetbundleName": "lottery_game\/new_year_2023_material",
    "omikujiCoverAssetbundleName": "lottery_game\/new_year_2023_material",
    "unitFilePath": "bird_Nightcord at 25_00",
    "fortuneFilePath": "unsei_cyukichi",
    "omikujiCoverFilePath": "omikuji_Nightcord at 25_00"
  },
  {
    "id": 81,
    "omikujiGroupId": 2,
    "unit": "school_refusal",
    "fortuneType": "small_fortune",
    "summary": "这一年中你可能会遇到\n许多迷茫和纠结，应当\n直面自己内心真实的感受。",
    "title1": "愿望",
    "description1": "只要有小小的期待，\n愿望就能实现。",
    "title2": "健康",
    "description2": "可能会遇到\n让你稍感疲惫的事。",
    "title3": "等候之人",
    "description3": "应当亲自创造邂逅良机。",
    "unitAssetbundleName": "lottery_game\/new_year_2023_material",
    "fortuneAssetbundleName": "lottery_game\/new_year_2023_material",
    "omikujiCoverAssetbundleName": "lottery_game\/new_year_2023_material",
    "unitFilePath": "bird_Nightcord at 25_00",
    "fortuneFilePath": "unsei_syoukichi",
    "omikujiCoverFilePath": "omikuji_Nightcord at 25_00"
  },
  {
    "id": 82,
    "omikujiGroupId": 2,
    "unit": "school_refusal",
    "fortuneType": "uncertain_luck",
    "summary": "这一年中\n学习新事物将对你的成长\n产生积极影响。",
    "title1": "愿望",
    "description1": "距离实现愿望会越来越近。",
    "title2": "健康",
    "description2": "要注意饮食均衡。",
    "title3": "等候之人",
    "description3": "会在不经意间相逢。",
    "unitAssetbundleName": "lottery_game\/new_year_2023_material",
    "fortuneAssetbundleName": "lottery_game\/new_year_2023_material",
    "omikujiCoverAssetbundleName": "lottery_game\/new_year_2023_material",
    "unitFilePath": "bird_Nightcord at 25_00",
    "fortuneFilePath": "unsei_suekichi",
    "omikujiCoverFilePath": "omikuji_Nightcord at 25_00"
  },
  {
    "id": 83,
    "omikujiGroupId": 2,
    "unit": "school_refusal",
    "fortuneType": "misfortune",
    "summary": "有迹象表明你与身边之人的\n关系可能会变得微妙，\n信赖朋友是正确的选择。",
    "title1": "愿望",
    "description1": "愿望不会同时实现。",
    "title2": "健康",
    "description2": "需要放松一下心灵。",
    "title3": "等候之人",
    "description3": "会有音讯。",
    "unitAssetbundleName": "lottery_game\/new_year_2023_material",
    "fortuneAssetbundleName": "lottery_game\/new_year_2023_material",
    "omikujiCoverAssetbundleName": "lottery_game\/new_year_2023_material",
    "unitFilePath": "bird_Nightcord at 25_00",
    "fortuneFilePath": "unsei_kyou",
    "omikujiCoverFilePath": "omikuji_Nightcord at 25_00"
  },
  {
    "id": 84,
    "omikujiGroupId": 2,
    "unit": "school_refusal",
    "fortuneType": "grate_misfortune",
    "summary": "这一年中困难与机遇并存，\n你需要直面这些问题，\n认清本质吧。",
    "title1": "愿望",
    "description1": "维持现状\n愿望应该很难实现。",
    "title2": "健康",
    "description2": "有精神疲劳的征兆，\n需多加留意。",
    "title3": "等候之人",
    "description3": "不会到来。",
    "unitAssetbundleName": "lottery_game\/new_year_2023_material",
    "fortuneAssetbundleName": "lottery_game\/new_year_2023_material",
    "omikujiCoverAssetbundleName": "lottery_game\/new_year_2023_material",
    "unitFilePath": "bird_Nightcord at 25_00",
    "fortuneFilePath": "unsei_daikyou",
    "omikujiCoverFilePath": "omikuji_Nightcord at 25_00"
  },
  {
    "id": 85,
    "omikujiGroupId": 3,
    "unit": "piapro",
    "fortuneType": "grate_fortune",
    "summary": "若持续祈愿，\n所孕育的事物，\n便会在今年开花结果。",
    "title1": "愿望",
    "description1": "愿望定将实现。",
    "title2": "健康",
    "description2": "情况非常好。",
    "title3": "等候之人",
    "description3": "一定会到来。",
    "unitAssetbundleName": "lottery_game\/new_year_2024_material",
    "fortuneAssetbundleName": "lottery_game\/new_year_2024_material",
    "omikujiCoverAssetbundleName": "lottery_game\/new_year_2024_material",
    "unitFilePath": "bird_VIRTUAL SINGER",
    "fortuneFilePath": "unsei_daikichi",
    "omikujiCoverFilePath": "omikuji_VIRTUAL SINGER"
  },
  {
    "id": 86,
    "omikujiGroupId": 3,
    "unit": "piapro",
    "fortuneType": "fortune",
    "summary": "若助人为乐，\n今年就会更加美好。",
    "title1": "愿望",
    "description1": "愿望能够实现。",
    "title2": "健康",
    "description2": "情况良好。",
    "title3": "等候之人",
    "description3": "会到来。\n且有音讯。",
    "unitAssetbundleName": "lottery_game\/new_year_2024_material",
    "fortuneAssetbundleName": "lottery_game\/new_year_2024_material",
    "omikujiCoverAssetbundleName": "lottery_game\/new_year_2024_material",
    "unitFilePath": "bird_VIRTUAL SINGER",
    "fortuneFilePath": "unsei_kichi",
    "omikujiCoverFilePath": "omikuji_VIRTUAL SINGER"
  },
  {
    "id": 87,
    "omikujiGroupId": 3,
    "unit": "piapro",
    "fortuneType": "middle_fortune",
    "summary": "你的言行可能会在\n不经意间帮到他人，\n按照自己的想法行动吧。",
    "title1": "愿望",
    "description1": "愿望应该能够实现。",
    "title2": "健康",
    "description2": "情况良好。",
    "title3": "等候之人",
    "description3": "虽然暂时没有音讯，\n但会到来。",
    "unitAssetbundleName": "lottery_game\/new_year_2024_material",
    "fortuneAssetbundleName": "lottery_game\/new_year_2024_material",
    "omikujiCoverAssetbundleName": "lottery_game\/new_year_2024_material",
    "unitFilePath": "bird_VIRTUAL SINGER",
    "fortuneFilePath": "unsei_cyukichi",
    "omikujiCoverFilePath": "omikuji_VIRTUAL SINGER"
  },
  {
    "id": 88,
    "omikujiGroupId": 3,
    "unit": "piapro",
    "fortuneType": "small_fortune",
    "summary": "你的经验\n可能会帮到他人，\n主动伸出援手吧。",
    "title1": "愿望",
    "description1": "若付出努力，愿望应该就能实现。",
    "title2": "健康",
    "description2": "少吃甜食。",
    "title3": "等候之人",
    "description3": "会有音讯。",
    "unitAssetbundleName": "lottery_game\/new_year_2024_material",
    "fortuneAssetbundleName": "lottery_game\/new_year_2024_material",
    "omikujiCoverAssetbundleName": "lottery_game\/new_year_2024_material",
    "unitFilePath": "bird_VIRTUAL SINGER",
    "fortuneFilePath": "unsei_syoukichi",
    "omikujiCoverFilePath": "omikuji_VIRTUAL SINGER"
  },
  {
    "id": 89,
    "omikujiGroupId": 3,
    "unit": "piapro",
    "fortuneType": "uncertain_luck",
    "summary": "尽管这一年充满坎坷，\n但只要心志坚定，\n你就能转化为机遇。",
    "title1": "愿望",
    "description1": "尽管会遇到困难，\n但愿望应该能够实现。",
    "title2": "健康",
    "description2": "情况良好。",
    "title3": "等候之人",
    "description3": "会晚来。",
    "unitAssetbundleName": "lottery_game\/new_year_2024_material",
    "fortuneAssetbundleName": "lottery_game\/new_year_2024_material",
    "omikujiCoverAssetbundleName": "lottery_game\/new_year_2024_material",
    "unitFilePath": "bird_VIRTUAL SINGER",
    "fortuneFilePath": "unsei_suekichi",
    "omikujiCoverFilePath": "omikuji_VIRTUAL SINGER"
  },
  {
    "id": 90,
    "omikujiGroupId": 3,
    "unit": "piapro",
    "fortuneType": "misfortune",
    "summary": "有迹象表明\n你的言行会招致麻烦，\n应当积极采纳他人的建议。",
    "title1": "愿望",
    "description1": "不要着急，静待良机。",
    "title2": "健康",
    "description2": "要适度运动。",
    "title3": "等候之人",
    "description3": "应当亲自创造邂逅良机。",
    "unitAssetbundleName": "lottery_game\/new_year_2024_material",
    "fortuneAssetbundleName": "lottery_game\/new_year_2024_material",
    "omikujiCoverAssetbundleName": "lottery_game\/new_year_2024_material",
    "unitFilePath": "bird_VIRTUAL SINGER",
    "fortuneFilePath": "unsei_kyou",
    "omikujiCoverFilePath": "omikuji_VIRTUAL SINGER"
  },
  {
    "id": 91,
    "omikujiGroupId": 3,
    "unit": "piapro",
    "fortuneType": "grate_misfortune",
    "summary": "有迹象表明\n你会因不顺之事感到心情郁闷，\n去寻求他人的帮助吧。",
    "title1": "愿望",
    "description1": "若维持现状，愿望无法实现。",
    "title2": "健康",
    "description2": "身心都不太稳定，\n需多加留意。",
    "title3": "等候之人",
    "description3": "不会到来。",
    "unitAssetbundleName": "lottery_game\/new_year_2024_material",
    "fortuneAssetbundleName": "lottery_game\/new_year_2024_material",
    "omikujiCoverAssetbundleName": "lottery_game\/new_year_2024_material",
    "unitFilePath": "bird_VIRTUAL SINGER",
    "fortuneFilePath": "unsei_daikyou",
    "omikujiCoverFilePath": "omikuji_VIRTUAL SINGER"
  },
  {
    "id": 92,
    "omikujiGroupId": 3,
    "unit": "light_sound",
    "fortuneType": "grate_fortune",
    "summary": "有迹象表明\n你之前的积累将会结出硕果，\n应该继续努力。",
    "title1": "愿望",
    "description1": "若下定决心，\n愿望就能够实现。",
    "title2": "健康",
    "description2": "情况非常好。",
    "title3": "等候之人",
    "description3": "一定会到来。",
    "unitAssetbundleName": "lottery_game\/new_year_2024_material",
    "fortuneAssetbundleName": "lottery_game\/new_year_2024_material",
    "omikujiCoverAssetbundleName": "lottery_game\/new_year_2024_material",
    "unitFilePath": "bird_Leoneed",
    "fortuneFilePath": "unsei_daikichi",
    "omikujiCoverFilePath": "omikuji_Leoneed"
  },
  {
    "id": 93,
    "omikujiGroupId": 3,
    "unit": "light_sound",
    "fortuneType": "fortune",
    "summary": "这一年中\n你会因环境变化感到困惑，\n行分内之事便能克服障碍。",
    "title1": "愿望",
    "description1": "与伙伴齐心协力，\n愿望就能实现。",
    "title2": "健康",
    "description2": "情况良好。",
    "title3": "等候之人",
    "description3": "会到来。",
    "unitAssetbundleName": "lottery_game\/new_year_2024_material",
    "fortuneAssetbundleName": "lottery_game\/new_year_2024_material",
    "omikujiCoverAssetbundleName": "lottery_game\/new_year_2024_material",
    "unitFilePath": "bird_Leoneed",
    "fortuneFilePath": "unsei_kichi",
    "omikujiCoverFilePath": "omikuji_Leoneed"
  },
  {
    "id": 94,
    "omikujiGroupId": 3,
    "unit": "light_sound",
    "fortuneType": "middle_fortune",
    "summary": "正视过去，\n这是解决问题的关键。",
    "title1": "愿望",
    "description1": "大胆表现愿望就能实现。",
    "title2": "健康",
    "description2": "不能勉强自己。",
    "title3": "等候之人",
    "description3": "会晚来。",
    "unitAssetbundleName": "lottery_game\/new_year_2024_material",
    "fortuneAssetbundleName": "lottery_game\/new_year_2024_material",
    "omikujiCoverAssetbundleName": "lottery_game\/new_year_2024_material",
    "unitFilePath": "bird_Leoneed",
    "fortuneFilePath": "unsei_cyukichi",
    "omikujiCoverFilePath": "omikuji_Leoneed"
  },
  {
    "id": 95,
    "omikujiGroupId": 3,
    "unit": "light_sound",
    "fortuneType": "small_fortune",
    "summary": "就算进展不顺利，\n只要不放弃，\n前进之路自然会为你敞开。",
    "title1": "愿望",
    "description1": "仰赖前人愿望就能实现。",
    "title2": "健康",
    "description2": "要注意饮食均衡。",
    "title3": "等候之人",
    "description3": "应当亲自创造邂逅良机。",
    "unitAssetbundleName": "lottery_game\/new_year_2024_material",
    "fortuneAssetbundleName": "lottery_game\/new_year_2024_material",
    "omikujiCoverAssetbundleName": "lottery_game\/new_year_2024_material",
    "unitFilePath": "bird_Leoneed",
    "fortuneFilePath": "unsei_syoukichi",
    "omikujiCoverFilePath": "omikuji_Leoneed"
  },
  {
    "id": 96,
    "omikujiGroupId": 3,
    "unit": "light_sound",
    "fortuneType": "uncertain_luck",
    "summary": "你可能会因\n事与愿违而烦恼。",
    "title1": "愿望",
    "description1": "只要坚持下去，\n前进的道路就会开启。",
    "title2": "健康",
    "description2": "有迹象表明你感到心力交瘁。",
    "title3": "等候之人",
    "description3": "会到来。",
    "unitAssetbundleName": "lottery_game\/new_year_2024_material",
    "fortuneAssetbundleName": "lottery_game\/new_year_2024_material",
    "omikujiCoverAssetbundleName": "lottery_game\/new_year_2024_material",
    "unitFilePath": "bird_Leoneed",
    "fortuneFilePath": "unsei_suekichi",
    "omikujiCoverFilePath": "omikuji_Leoneed"
  },
  {
    "id": 97,
    "omikujiGroupId": 3,
    "unit": "light_sound",
    "fortuneType": "misfortune",
    "summary": "这一年中\n你的言行可能招致误会，\n发言前需慎重考虑。",
    "title1": "愿望",
    "description1": "愿望现在还无法实现。",
    "title2": "健康",
    "description2": "没有问题。",
    "title3": "等候之人",
    "description3": "会晚来。",
    "unitAssetbundleName": "lottery_game\/new_year_2024_material",
    "fortuneAssetbundleName": "lottery_game\/new_year_2024_material",
    "omikujiCoverAssetbundleName": "lottery_game\/new_year_2024_material",
    "unitFilePath": "bird_Leoneed",
    "fortuneFilePath": "unsei_kyou",
    "omikujiCoverFilePath": "omikuji_Leoneed"
  },
  {
    "id": 98,
    "omikujiGroupId": 3,
    "unit": "light_sound",
    "fortuneType": "grate_misfortune",
    "summary": "有些困难难以\n依靠自身努力解决，\n去寻求他人的帮助吧。",
    "title1": "愿望",
    "description1": "若维持现状，\n愿望很难实现。",
    "title2": "健康",
    "description2": "少吃甜食。",
    "title3": "等候之人",
    "description3": "应该会到来。",
    "unitAssetbundleName": "lottery_game\/new_year_2024_material",
    "fortuneAssetbundleName": "lottery_game\/new_year_2024_material",
    "omikujiCoverAssetbundleName": "lottery_game\/new_year_2024_material",
    "unitFilePath": "bird_Leoneed",
    "fortuneFilePath": "unsei_daikyou",
    "omikujiCoverFilePath": "omikuji_Leoneed"
  },
  {
    "id": 99,
    "omikujiGroupId": 3,
    "unit": "idol",
    "fortuneType": "grate_fortune",
    "summary": "这一年中不懈的努力\n会开花结果，你将遇到\n实现梦想的转折点。",
    "title1": "愿望",
    "description1": "万事小心愿望就能实现。",
    "title2": "健康",
    "description2": "只要坚持运动，\n身体状况就会变好。",
    "title3": "等候之人",
    "description3": "应该会到来。",
    "unitAssetbundleName": "lottery_game\/new_year_2024_material",
    "fortuneAssetbundleName": "lottery_game\/new_year_2024_material",
    "omikujiCoverAssetbundleName": "lottery_game\/new_year_2024_material",
    "unitFilePath": "bird_MORE MORE JUMP",
    "fortuneFilePath": "unsei_daikichi",
    "omikujiCoverFilePath": "omikuji_MORE MORE JUMP"
  },
  {
    "id": 100,
    "omikujiGroupId": 3,
    "unit": "idol",
    "fortuneType": "fortune",
    "summary": "这一年中你会得到许多\n与各种人交流的机会，\n享受充满活力的日常生活吧。",
    "title1": "愿望",
    "description1": "会得到朋友的帮助，\n愿望能够实现。",
    "title2": "健康",
    "description2": "甜食有助于缓解疲劳。",
    "title3": "等候之人",
    "description3": "会到来。",
    "unitAssetbundleName": "lottery_game\/new_year_2024_material",
    "fortuneAssetbundleName": "lottery_game\/new_year_2024_material",
    "omikujiCoverAssetbundleName": "lottery_game\/new_year_2024_material",
    "unitFilePath": "bird_MORE MORE JUMP",
    "fortuneFilePath": "unsei_kichi",
    "omikujiCoverFilePath": "omikuji_MORE MORE JUMP"
  },
  {
    "id": 101,
    "omikujiGroupId": 3,
    "unit": "idol",
    "fortuneType": "middle_fortune",
    "summary": "这一年中\n你会迎来重大的转机，\n需要做出大胆的决定。",
    "title1": "愿望",
    "description1": "至今的努力会得到回报，\n愿望能够实现。",
    "title2": "健康",
    "description2": "情况良好。",
    "title3": "等候之人",
    "description3": "会有音讯。",
    "unitAssetbundleName": "lottery_game\/new_year_2024_material",
    "fortuneAssetbundleName": "lottery_game\/new_year_2024_material",
    "omikujiCoverAssetbundleName": "lottery_game\/new_year_2024_material",
    "unitFilePath": "bird_MORE MORE JUMP",
    "fortuneFilePath": "unsei_cyukichi",
    "omikujiCoverFilePath": "omikuji_MORE MORE JUMP"
  },
  {
    "id": 102,
    "omikujiGroupId": 3,
    "unit": "idol",
    "fortuneType": "small_fortune",
    "summary": "虽然事情可能不能\n如你所愿，但最终时间\n会解决一切。",
    "title1": "愿望",
    "description1": "一开始很难实现愿望，\n但会逐渐顺利起来。",
    "title2": "健康",
    "description2": "没有问题。",
    "title3": "等候之人",
    "description3": "不会到来。",
    "unitAssetbundleName": "lottery_game\/new_year_2024_material",
    "fortuneAssetbundleName": "lottery_game\/new_year_2024_material",
    "omikujiCoverAssetbundleName": "lottery_game\/new_year_2024_material",
    "unitFilePath": "bird_MORE MORE JUMP",
    "fortuneFilePath": "unsei_syoukichi",
    "omikujiCoverFilePath": "omikuji_MORE MORE JUMP"
  },
  {
    "id": 103,
    "omikujiGroupId": 3,
    "unit": "idol",
    "fortuneType": "uncertain_luck",
    "summary": "这一年中你会感到犹豫迷茫，\n被迫面临许多选择，\n相信自己的决定吧。",
    "title1": "愿望",
    "description1": "若维持现状，\n愿望很难实现。",
    "title2": "健康",
    "description2": "没有问题。",
    "title3": "等候之人",
    "description3": "应该会到来。",
    "unitAssetbundleName": "lottery_game\/new_year_2024_material",
    "fortuneAssetbundleName": "lottery_game\/new_year_2024_material",
    "omikujiCoverAssetbundleName": "lottery_game\/new_year_2024_material",
    "unitFilePath": "bird_MORE MORE JUMP",
    "fortuneFilePath": "unsei_suekichi",
    "omikujiCoverFilePath": "omikuji_MORE MORE JUMP"
  },
  {
    "id": 104,
    "omikujiGroupId": 3,
    "unit": "idol",
    "fortuneType": "misfortune",
    "summary": "有迹象表明旧日的因缘或纠纷\n可能会给你造成麻烦，\n需多加留意。",
    "title1": "愿望",
    "description1": "会得到许多帮助，\n愿望应该能实现。",
    "title2": "健康",
    "description2": "没有问题。",
    "title3": "等候之人",
    "description3": "会不期而至。",
    "unitAssetbundleName": "lottery_game\/new_year_2024_material",
    "fortuneAssetbundleName": "lottery_game\/new_year_2024_material",
    "omikujiCoverAssetbundleName": "lottery_game\/new_year_2024_material",
    "unitFilePath": "bird_MORE MORE JUMP",
    "fortuneFilePath": "unsei_kyou",
    "omikujiCoverFilePath": "omikuji_MORE MORE JUMP"
  },
  {
    "id": 105,
    "omikujiGroupId": 3,
    "unit": "idol",
    "fortuneType": "grate_misfortune",
    "summary": "这一年中你会遇到\n巨大的机挑战，要有坚强的\n耐心和毅力去面对。",
    "title1": "愿望",
    "description1": "虽然愿望会实现，\n但不会完全如你所愿。",
    "title2": "健康",
    "description2": "有迹象表明你心力交瘁的\n情况很严重，请务必注意。",
    "title3": "等候之人",
    "description3": "会有音讯。",
    "unitAssetbundleName": "lottery_game\/new_year_2024_material",
    "fortuneAssetbundleName": "lottery_game\/new_year_2024_material",
    "omikujiCoverAssetbundleName": "lottery_game\/new_year_2024_material",
    "unitFilePath": "bird_MORE MORE JUMP",
    "fortuneFilePath": "unsei_daikyou",
    "omikujiCoverFilePath": "omikuji_MORE MORE JUMP"
  },
  {
    "id": 106,
    "omikujiGroupId": 3,
    "unit": "street",
    "fortuneType": "grate_fortune",
    "summary": "你离梦想又近了一步，\n将获得宝贵的经验。",
    "title1": "愿望",
    "description1": "磨练实力愿望就会实现，\n需努力修行。",
    "title2": "健康",
    "description2": "情况非常好。",
    "title3": "等候之人",
    "description3": "会到来。",
    "unitAssetbundleName": "lottery_game\/new_year_2024_material",
    "fortuneAssetbundleName": "lottery_game\/new_year_2024_material",
    "omikujiCoverAssetbundleName": "lottery_game\/new_year_2024_material",
    "unitFilePath": "bird_Vivid BAD SQUAD",
    "fortuneFilePath": "unsei_daikichi",
    "omikujiCoverFilePath": "omikuji_Vivid BAD SQUAD"
  },
  {
    "id": 107,
    "omikujiGroupId": 3,
    "unit": "street",
    "fortuneType": "fortune",
    "summary": "你会找到一种与人交往时，\n充分发挥才能的方法。",
    "title1": "愿望",
    "description1": "会得到前人的指导，\n愿望应该能够实现。",
    "title2": "健康",
    "description2": "情况良好。",
    "title3": "等候之人",
    "description3": "会到来。",
    "unitAssetbundleName": "lottery_game\/new_year_2024_material",
    "fortuneAssetbundleName": "lottery_game\/new_year_2024_material",
    "omikujiCoverAssetbundleName": "lottery_game\/new_year_2024_material",
    "unitFilePath": "bird_Vivid BAD SQUAD",
    "fortuneFilePath": "unsei_kichi",
    "omikujiCoverFilePath": "omikuji_Vivid BAD SQUAD"
  },
  {
    "id": 108,
    "omikujiGroupId": 3,
    "unit": "street",
    "fortuneType": "middle_fortune",
    "summary": "这一年中你会更加\n关注你的梦想与希望，\n需继续努力。",
    "title1": "愿望",
    "description1": "只要强烈期待，\n愿望应该就能实现。",
    "title2": "健康",
    "description2": "情况良好。",
    "title3": "等候之人",
    "description3": "会不期而至。",
    "unitAssetbundleName": "lottery_game\/new_year_2024_material",
    "fortuneAssetbundleName": "lottery_game\/new_year_2024_material",
    "omikujiCoverAssetbundleName": "lottery_game\/new_year_2024_material",
    "unitFilePath": "bird_Vivid BAD SQUAD",
    "fortuneFilePath": "unsei_cyukichi",
    "omikujiCoverFilePath": "omikuji_Vivid BAD SQUAD"
  },
  {
    "id": 109,
    "omikujiGroupId": 3,
    "unit": "street",
    "fortuneType": "small_fortune",
    "summary": "有迹象表明你会因\n意外之事而摇摆不定，\n需坚定自己的意志。",
    "title1": "愿望",
    "description1": "与旁人商量愿望就会实现，\n应当重视与伙伴的交流。",
    "title2": "健康",
    "description2": "可能会感到心力交瘁。",
    "title3": "等候之人",
    "description3": "应该很快就会到来。",
    "unitAssetbundleName": "lottery_game\/new_year_2024_material",
    "fortuneAssetbundleName": "lottery_game\/new_year_2024_material",
    "omikujiCoverAssetbundleName": "lottery_game\/new_year_2024_material",
    "unitFilePath": "bird_Vivid BAD SQUAD",
    "fortuneFilePath": "unsei_syoukichi",
    "omikujiCoverFilePath": "omikuji_Vivid BAD SQUAD"
  },
  {
    "id": 110,
    "omikujiGroupId": 3,
    "unit": "street",
    "fortuneType": "uncertain_luck",
    "summary": "你将有机会斩断过去的因缘，\n一旦跨过这一步，\n便前途无量。",
    "title1": "愿望",
    "description1": "只要拥有坚强的意志，\n愿望就会实现。",
    "title2": "健康",
    "description2": "情况非常好。\n建议坚持运动。",
    "title3": "等候之人",
    "description3": "应该会到来。",
    "unitAssetbundleName": "lottery_game\/new_year_2024_material",
    "fortuneAssetbundleName": "lottery_game\/new_year_2024_material",
    "omikujiCoverAssetbundleName": "lottery_game\/new_year_2024_material",
    "unitFilePath": "bird_Vivid BAD SQUAD",
    "fortuneFilePath": "unsei_suekichi",
    "omikujiCoverFilePath": "omikuji_Vivid BAD SQUAD"
  },
  {
    "id": 111,
    "omikujiGroupId": 3,
    "unit": "street",
    "fortuneType": "misfortune",
    "summary": "有迹象表明\n不顺心的事情可能会\n接踵而至。",
    "title1": "愿望",
    "description1": "愿望应该很难实现。",
    "title2": "健康",
    "description2": "没有问题。",
    "title3": "等候之人",
    "description3": "虽然会到来，\n但不会很快。",
    "unitAssetbundleName": "lottery_game\/new_year_2024_material",
    "fortuneAssetbundleName": "lottery_game\/new_year_2024_material",
    "omikujiCoverAssetbundleName": "lottery_game\/new_year_2024_material",
    "unitFilePath": "bird_Vivid BAD SQUAD",
    "fortuneFilePath": "unsei_kyou",
    "omikujiCoverFilePath": "omikuji_Vivid BAD SQUAD"
  },
  {
    "id": 112,
    "omikujiGroupId": 3,
    "unit": "street",
    "fortuneType": "grate_misfortune",
    "summary": "有迹象表明你会因为自己\n不如周围的人而感到自卑。\n继续努力不要放弃。",
    "title1": "愿望",
    "description1": "愿望距离实现还很遥远，\n但只要努力就会有所进展。",
    "title2": "健康",
    "description2": "没有问题。",
    "title3": "等候之人",
    "description3": "会晚来。",
    "unitAssetbundleName": "lottery_game\/new_year_2024_material",
    "fortuneAssetbundleName": "lottery_game\/new_year_2024_material",
    "omikujiCoverAssetbundleName": "lottery_game\/new_year_2024_material",
    "unitFilePath": "bird_Vivid BAD SQUAD",
    "fortuneFilePath": "unsei_daikyou",
    "omikujiCoverFilePath": "omikuji_Vivid BAD SQUAD"
  },
  {
    "id": 113,
    "omikujiGroupId": 3,
    "unit": "theme_park",
    "fortuneType": "grate_fortune",
    "summary": "这一年中你会通过各种经历，\n朝梦想大步迈进。",
    "title1": "愿望",
    "description1": "愿望应该能够实现。",
    "title2": "健康",
    "description2": "情况非常好。",
    "title3": "等候之人",
    "description3": "一定会到来。",
    "unitAssetbundleName": "lottery_game\/new_year_2024_material",
    "fortuneAssetbundleName": "lottery_game\/new_year_2024_material",
    "omikujiCoverAssetbundleName": "lottery_game\/new_year_2024_material",
    "unitFilePath": "bird_Wonderlands×Showtime",
    "fortuneFilePath": "unsei_daikichi",
    "omikujiCoverFilePath": "omikuji_Wonderlands×Showtime"
  },
  {
    "id": 114,
    "omikujiGroupId": 3,
    "unit": "theme_park",
    "fortuneType": "fortune",
    "summary": "这一年中你会克服自身障碍\n得到成长，过去的经验是\n解决问题的关键。",
    "title1": "愿望",
    "description1": "有努力相伴，\n愿望就一定能实现。",
    "title2": "健康",
    "description2": "情况良好。",
    "title3": "等候之人",
    "description3": "一定会到来。",
    "unitAssetbundleName": "lottery_game\/new_year_2024_material",
    "fortuneAssetbundleName": "lottery_game\/new_year_2024_material",
    "omikujiCoverAssetbundleName": "lottery_game\/new_year_2024_material",
    "unitFilePath": "bird_Wonderlands×Showtime",
    "fortuneFilePath": "unsei_kichi",
    "omikujiCoverFilePath": "omikuji_Wonderlands×Showtime"
  },
  {
    "id": 115,
    "omikujiGroupId": 3,
    "unit": "theme_park",
    "fortuneType": "middle_fortune",
    "summary": "遇事不决时，唯有坚定\n自己的信念为梦想全力以赴\n才是捷径。",
    "title1": "愿望",
    "description1": "在伙伴们的帮助下\n愿望能够实现。",
    "title2": "健康",
    "description2": "情况良好。",
    "title3": "等候之人",
    "description3": "会到来。",
    "unitAssetbundleName": "lottery_game\/new_year_2024_material",
    "fortuneAssetbundleName": "lottery_game\/new_year_2024_material",
    "omikujiCoverAssetbundleName": "lottery_game\/new_year_2024_material",
    "unitFilePath": "bird_Wonderlands×Showtime",
    "fortuneFilePath": "unsei_cyukichi",
    "omikujiCoverFilePath": "omikuji_Wonderlands×Showtime"
  },
  {
    "id": 116,
    "omikujiGroupId": 3,
    "unit": "theme_park",
    "fortuneType": "small_fortune",
    "summary": "即使遇到困难，只要\n勇于挑战，你就能获得\n显著的成长和进步。",
    "title1": "愿望",
    "description1": "持续努力，\n应该就会看见希望。",
    "title2": "健康",
    "description2": "有受伤的可能性。",
    "title3": "等候之人",
    "description3": "会晚来。",
    "unitAssetbundleName": "lottery_game\/new_year_2024_material",
    "fortuneAssetbundleName": "lottery_game\/new_year_2024_material",
    "omikujiCoverAssetbundleName": "lottery_game\/new_year_2024_material",
    "unitFilePath": "bird_Wonderlands×Showtime",
    "fortuneFilePath": "unsei_syoukichi",
    "omikujiCoverFilePath": "omikuji_Wonderlands×Showtime"
  },
  {
    "id": 117,
    "omikujiGroupId": 3,
    "unit": "theme_park",
    "fortuneType": "uncertain_luck",
    "summary": "这一年中你会关注自己的心愿，\n在感到迷茫无措时，\n聆听内心的声音是明智之举。",
    "title1": "愿望",
    "description1": "会找到实现愿望之路。",
    "title2": "健康",
    "description2": "没有问题。",
    "title3": "等候之人",
    "description3": "会到来。",
    "unitAssetbundleName": "lottery_game\/new_year_2024_material",
    "fortuneAssetbundleName": "lottery_game\/new_year_2024_material",
    "omikujiCoverAssetbundleName": "lottery_game\/new_year_2024_material",
    "unitFilePath": "bird_Wonderlands×Showtime",
    "fortuneFilePath": "unsei_suekichi",
    "omikujiCoverFilePath": "omikuji_Wonderlands×Showtime"
  },
  {
    "id": 118,
    "omikujiGroupId": 3,
    "unit": "theme_park",
    "fortuneType": "misfortune",
    "summary": "切勿仓促行动，\n应当先面对眼前的事物。",
    "title1": "愿望",
    "description1": "还需要努力。",
    "title2": "健康",
    "description2": "有迹象表明你心慌意乱。",
    "title3": "等候之人",
    "description3": "应当亲自创造邂逅良机。",
    "unitAssetbundleName": "lottery_game\/new_year_2024_material",
    "fortuneAssetbundleName": "lottery_game\/new_year_2024_material",
    "omikujiCoverAssetbundleName": "lottery_game\/new_year_2024_material",
    "unitFilePath": "bird_Wonderlands×Showtime",
    "fortuneFilePath": "unsei_kyou",
    "omikujiCoverFilePath": "omikuji_Wonderlands×Showtime"
  },
  {
    "id": 119,
    "omikujiGroupId": 3,
    "unit": "theme_park",
    "fortuneType": "grate_misfortune",
    "summary": "你可能会遭遇\n意想不到的事故，\n出行时要多加注意。",
    "title1": "愿望",
    "description1": "愿望现在还无法实现。",
    "title2": "健康",
    "description2": "要增强基础体力。",
    "title3": "等候之人",
    "description3": "虽然会到来，\n但不会很快。",
    "unitAssetbundleName": "lottery_game\/new_year_2024_material",
    "fortuneAssetbundleName": "lottery_game\/new_year_2024_material",
    "omikujiCoverAssetbundleName": "lottery_game\/new_year_2024_material",
    "unitFilePath": "bird_Wonderlands×Showtime",
    "fortuneFilePath": "unsei_daikyou",
    "omikujiCoverFilePath": "omikuji_Wonderlands×Showtime"
  },
  {
    "id": 120,
    "omikujiGroupId": 3,
    "unit": "school_refusal",
    "fortuneType": "grate_fortune",
    "summary": "这一年中将会充满机遇，\n你同各种人相遇交流，\n带来新的转机。",
    "title1": "愿望",
    "description1": "付出努力愿望就能实现。",
    "title2": "健康",
    "description2": "情况非常好。",
    "title3": "等候之人",
    "description3": "一定会到来。",
    "unitAssetbundleName": "lottery_game\/new_year_2024_material",
    "fortuneAssetbundleName": "lottery_game\/new_year_2024_material",
    "omikujiCoverAssetbundleName": "lottery_game\/new_year_2024_material",
    "unitFilePath": "bird_Nightcord at 25_00",
    "fortuneFilePath": "unsei_daikichi",
    "omikujiCoverFilePath": "omikuji_Nightcord at 25_00"
  },
  {
    "id": 121,
    "omikujiGroupId": 3,
    "unit": "school_refusal",
    "fortuneType": "fortune",
    "summary": "即使你现在很艰苦，\n但终有一天你能找到\n舒适的容身之处。",
    "title1": "愿望",
    "description1": "愿望应该能够实现。",
    "title2": "健康",
    "description2": "没有问题。",
    "title3": "等候之人",
    "description3": "会到来。",
    "unitAssetbundleName": "lottery_game\/new_year_2024_material",
    "fortuneAssetbundleName": "lottery_game\/new_year_2024_material",
    "omikujiCoverAssetbundleName": "lottery_game\/new_year_2024_material",
    "unitFilePath": "bird_Nightcord at 25_00",
    "fortuneFilePath": "unsei_kichi",
    "omikujiCoverFilePath": "omikuji_Nightcord at 25_00"
  },
  {
    "id": 122,
    "omikujiGroupId": 3,
    "unit": "school_refusal",
    "fortuneType": "middle_fortune",
    "summary": "你将通过他人获得\n许多相遇交流的机会，\n多出去走走吧。",
    "title1": "愿望",
    "description1": "会得到他人的帮助，\n实现愿望。",
    "title2": "健康",
    "description2": "要转换一下心情。",
    "title3": "等候之人",
    "description3": "会在不经意间相逢。",
    "unitAssetbundleName": "lottery_game\/new_year_2024_material",
    "fortuneAssetbundleName": "lottery_game\/new_year_2024_material",
    "omikujiCoverAssetbundleName": "lottery_game\/new_year_2024_material",
    "unitFilePath": "bird_Nightcord at 25_00",
    "fortuneFilePath": "unsei_cyukichi",
    "omikujiCoverFilePath": "omikuji_Nightcord at 25_00"
  },
  {
    "id": 123,
    "omikujiGroupId": 3,
    "unit": "school_refusal",
    "fortuneType": "small_fortune",
    "summary": "这一年中你可能会遇到\n许多迷茫和纠结，应当\n直面自己内心真实的感受。",
    "title1": "愿望",
    "description1": "只要有小小的期待，\n愿望就能实现。",
    "title2": "健康",
    "description2": "可能会遇到\n让你稍感疲惫的事。",
    "title3": "等候之人",
    "description3": "应当亲自创造邂逅良机。",
    "unitAssetbundleName": "lottery_game\/new_year_2024_material",
    "fortuneAssetbundleName": "lottery_game\/new_year_2024_material",
    "omikujiCoverAssetbundleName": "lottery_game\/new_year_2024_material",
    "unitFilePath": "bird_Nightcord at 25_00",
    "fortuneFilePath": "unsei_syoukichi",
    "omikujiCoverFilePath": "omikuji_Nightcord at 25_00"
  },
  {
    "id": 124,
    "omikujiGroupId": 3,
    "unit": "school_refusal",
    "fortuneType": "uncertain_luck",
    "summary": "这一年中\n学习新事物将对你的成长\n产生积极影响。",
    "title1": "愿望",
    "description1": "距离实现愿望会越来越近。",
    "title2": "健康",
    "description2": "要注意饮食均衡。",
    "title3": "等候之人",
    "description3": "会在不经意间相逢。",
    "unitAssetbundleName": "lottery_game\/new_year_2024_material",
    "fortuneAssetbundleName": "lottery_game\/new_year_2024_material",
    "omikujiCoverAssetbundleName": "lottery_game\/new_year_2024_material",
    "unitFilePath": "bird_Nightcord at 25_00",
    "fortuneFilePath": "unsei_suekichi",
    "omikujiCoverFilePath": "omikuji_Nightcord at 25_00"
  },
  {
    "id": 125,
    "omikujiGroupId": 3,
    "unit": "school_refusal",
    "fortuneType": "misfortune",
    "summary": "有迹象表明你与身边之人的\n关系可能会变得微妙，\n信赖朋友是正确的选择。",
    "title1": "愿望",
    "description1": "愿望不会同时实现。",
    "title2": "健康",
    "description2": "需要放松一下心灵。",
    "title3": "等候之人",
    "description3": "会有音讯。",
    "unitAssetbundleName": "lottery_game\/new_year_2024_material",
    "fortuneAssetbundleName": "lottery_game\/new_year_2024_material",
    "omikujiCoverAssetbundleName": "lottery_game\/new_year_2024_material",
    "unitFilePath": "bird_Nightcord at 25_00",
    "fortuneFilePath": "unsei_kyou",
    "omikujiCoverFilePath": "omikuji_Nightcord at 25_00"
  },
  {
    "id": 126,
    "omikujiGroupId": 3,
    "unit": "school_refusal",
    "fortuneType": "grate_misfortune",
    "summary": "这一年中困难与机遇并存，\n 你需要直面这些问题，\n 认清本质吧。",
    "title1": "愿望",
    "description1": "维持现状\n愿望应该很难实现。",
    "title2": "健康",
    "description2": "有精神疲劳的征兆，\n需多加留意。",
    "title3": "等候之人",
    "description3": "不会到来。",
    "unitAssetbundleName": "lottery_game\/new_year_2024_material",
    "fortuneAssetbundleName": "lottery_game\/new_year_2024_material",
    "omikujiCoverAssetbundleName": "lottery_game\/new_year_2024_material",
    "unitFilePath": "bird_Nightcord at 25_00",
    "fortuneFilePath": "unsei_daikyou",
    "omikujiCoverFilePath": "omikuji_Nightcord at 25_00"
  }
]